{
  "items": [
    {
      "ticker": "VT",
      "start_date": "2024-05-01",
      "end_date": "2025-10-29",
      "start_price": 103.444954,
      "end_price": 141.589996,
      "total_return": 0.3687472513110919,
      "cagr": 0.23365654944177017,
      "total_return_pct": 36.8747,
      "cagr_pct": 23.3657
    },
    {
      "ticker": "MSFT",
      "start_date": "2024-05-01",
      "end_date": "2025-10-29",
      "start_price": 390.58728,
      "end_price": 541.549988,
      "total_return": 0.38650185283516447,
      "cagr": 0.2443385205980697,
      "total_return_pct": 38.6502,
      "cagr_pct": 24.4339
    },
    {
      "ticker": "AAPL",
      "start_date": "2024-05-01",
      "end_date": "2025-10-29",
      "start_price": 168.092896,
      "end_price": 269.700012,
      "total_return": 0.6044700246983152,
      "cagr": 0.3720117164428727,
      "total_return_pct": 60.447,
      "cagr_pct": 37.2012
    },
    {
      "ticker": "NVDA",
      "start_date": "2024-05-01",
      "end_date": "2025-10-29",
      "start_price": 83.003265,
      "end_price": 207.039993,
      "total_return": 1.4943596174937523,
      "cagr": 0.8430968929259186,
      "total_return_pct": 149.436,
      "cagr_pct": 84.3097
    },
    {
      "ticker": "AMZN",
      "start_date": "2024-05-01",
      "end_date": "2025-10-29",
      "start_price": 179.0,
      "end_price": 230.300003,
      "total_return": 0.28659219581987605,
      "cagr": 0.18361690688670396,
      "total_return_pct": 28.6592,
      "cagr_pct": 18.3617
    },
    {
      "ticker": "GOOGL",
      "start_date": "2024-05-01",
      "end_date": "2025-10-29",
      "start_price": 162.737579,
      "end_price": 274.570007,
      "total_return": 0.6871948595287276,
      "cagr": 0.4189384676024923,
      "total_return_pct": 68.7195,
      "cagr_pct": 41.8938
    },
    {
      "ticker": "META",
      "start_date": "2024-05-01",
      "end_date": "2025-10-29",
      "start_price": 436.96225,
      "end_price": 751.669983,
      "total_return": 0.7202172117388428,
      "cagr": 0.43745700907319374,
      "total_return_pct": 72.0217,
      "cagr_pct": 43.7457
    },
    {
      "ticker": "GOOG",
      "start_date": "2024-05-01",
      "end_date": "2025-10-29",
      "start_price": 164.444672,
      "end_price": 275.170013,
      "total_return": 0.6733288509671389,
      "cagr": 0.41112686923940234,
      "total_return_pct": 67.3329,
      "cagr_pct": 41.1127
    },
    {
      "ticker": "LLY",
      "start_date": "2024-05-01",
      "end_date": "2025-10-29",
      "start_price": 768.46936,
      "end_price": 813.530029,
      "total_return": 0.058636910292295896,
      "cagr": 0.03885438340345648,
      "total_return_pct": 5.8637,
      "cagr_pct": 3.8854
    },
    {
      "ticker": "BRK-B",
      "start_date": "2024-05-01",
      "end_date": "2025-10-29",
      "start_price": 398.579987,
      "end_price": 475.76001,
      "total_return": 0.1936374775289076,
      "cagr": 0.12570420275524885,
      "total_return_pct": 19.3637,
      "cagr_pct": 12.5704
    },
    {
      "ticker": "2330.TW",
      "start_date": "2024-05-02",
      "end_date": "2025-10-30",
      "start_price": 752.925476,
      "end_price": 1505.0,
      "total_return": 0.9988698056109426,
      "cagr": 0.5893209725913768,
      "total_return_pct": 99.887,
      "cagr_pct": 58.9321
    },
    {
      "ticker": "AVGO",
      "start_date": "2024-05-01",
      "end_date": "2025-10-29",
      "start_price": 122.287102,
      "end_price": 385.980011,
      "total_return": 2.1563427824897223,
      "cagr": 1.1574078876113352,
      "total_return_pct": 215.6343,
      "cagr_pct": 115.7408
    },
    {
      "ticker": "JPM",
      "start_date": "2024-05-01",
      "end_date": "2025-10-29",
      "start_price": 185.709351,
      "end_price": 305.51001,
      "total_return": 0.6450976151803913,
      "cagr": 0.39515585545775744,
      "total_return_pct": 64.5098,
      "cagr_pct": 39.5156
    },
    {
      "ticker": "TSLA",
      "start_date": "2024-05-01",
      "end_date": "2025-10-29",
      "start_price": 179.990005,
      "end_price": 461.51001,
      "total_return": 1.5640868697187353,
      "cagr": 0.8774052347485926,
      "total_return_pct": 156.4087,
      "cagr_pct": 87.7405
    },
    {
      "ticker": "XOM",
      "start_date": "2024-05-01",
      "end_date": "2025-10-29",
      "start_price": 110.191711,
      "end_price": 116.449997,
      "total_return": 0.05679452148881592,
      "cagr": 0.03764458865282316,
      "total_return_pct": 5.6795,
      "cagr_pct": 3.7645
    },
    {
      "ticker": "UNH",
      "start_date": "2024-05-01",
      "end_date": "2025-10-29",
      "start_price": 470.164948,
      "end_price": 355.26001,
      "total_return": -0.24439282075947177,
      "cagr": -0.17094102674222145,
      "total_return_pct": -24.4393,
      "cagr_pct": -17.0941
    },
    {
      "ticker": "V",
      "start_date": "2024-05-01",
      "end_date": "2025-10-29",
      "start_price": 264.43515,
      "end_price": 341.279999,
      "total_return": 0.29059997731105014,
      "cagr": 0.1860820843601445,
      "total_return_pct": 29.06,
      "cagr_pct": 18.6082
    },
    {
      "ticker": "NVO",
      "start_date": "2024-05-01",
      "end_date": "2025-10-29",
      "start_price": 126.686729,
      "end_price": 51.369999,
      "total_return": -0.594511602260585,
      "cagr": -0.4532927881658628,
      "total_return_pct": -59.4512,
      "cagr_pct": -45.3293
    },
    {
      "ticker": "PG",
      "start_date": "2024-05-01",
      "end_date": "2025-10-29",
      "start_price": 157.317398,
      "end_price": 148.770004,
      "total_return": -0.054332158449218904,
      "cagr": -0.03668082815503815,
      "total_return_pct": -5.4332,
      "cagr_pct": -3.6681
    },
    {
      "ticker": "MA",
      "start_date": "2024-05-01",
      "end_date": "2025-10-29",
      "start_price": 438.311707,
      "end_price": 554.580017,
      "total_return": 0.2652639863623558,
      "cagr": 0.170454931222207,
      "total_return_pct": 26.5264,
      "cagr_pct": 17.0455
    },
    {
      "ticker": "JNJ",
      "start_date": "2024-05-01",
      "end_date": "2025-10-29",
      "start_price": 144.177399,
      "end_price": 186.600006,
      "total_return": 0.2942389570750179,
      "cagr": 0.18831821840252805,
      "total_return_pct": 29.4239,
      "cagr_pct": 18.8318
    },
    {
      "ticker": "ASML",
      "start_date": "2024-05-01",
      "end_date": "2025-10-29",
      "start_price": 841.258301,
      "end_price": 1070.839966,
      "total_return": 0.2729027039921714,
      "cagr": 0.17517728522660736,
      "total_return_pct": 27.2903,
      "cagr_pct": 17.5177
    },
    {
      "ticker": "HD",
      "start_date": "2024-05-01",
      "end_date": "2025-10-29",
      "start_price": 320.099121,
      "end_price": 378.040009,
      "total_return": 0.18100920506495943,
      "cagr": 0.11772321198009594,
      "total_return_pct": 18.1009,
      "cagr_pct": 11.7723
    },
    {
      "ticker": "MRK",
      "start_date": "2024-05-01",
      "end_date": "2025-10-29",
      "start_price": 122.640961,
      "end_price": 86.580002,
      "total_return": -0.2940368263460389,
      "cagr": -0.20778723444453762,
      "total_return_pct": -29.4037,
      "cagr_pct": -20.7787
    },
    {
      "ticker": "COST",
      "start_date": "2024-05-01",
      "end_date": "2025-10-29",
      "start_price": 717.511047,
      "end_price": 912.419983,
      "total_return": 0.2716459018479629,
      "cagr": 0.174400960041319,
      "total_return_pct": 27.1646,
      "cagr_pct": 17.4401
    },
    {
      "ticker": "ABBV",
      "start_date": "2024-05-01",
      "end_date": "2025-10-29",
      "start_price": 153.607407,
      "end_price": 225.139999,
      "total_return": 0.46568452882068456,
      "cagr": 0.2914387055442995,
      "total_return_pct": 46.5685,
      "cagr_pct": 29.1439
    },
    {
      "ticker": "CVX",
      "start_date": "2024-05-01",
      "end_date": "2025-10-29",
      "start_price": 149.504196,
      "end_price": 155.100006,
      "total_return": 0.03742911623880496,
      "cagr": 0.024885833103254207,
      "total_return_pct": 3.7429,
      "cagr_pct": 2.4886
    },
    {
      "ticker": "7203.T",
      "start_date": "2024-05-01",
      "end_date": "2025-10-30",
      "start_price": 3436.442871,
      "end_price": 3178.0,
      "total_return": -0.07520650881982882,
      "cagr": -0.05086723557101713,
      "total_return_pct": -7.5207,
      "cagr_pct": -5.0867
    },
    {
      "ticker": "0700.HK",
      "start_date": "2024-05-02",
      "end_date": "2025-10-30",
      "start_price": 354.221313,
      "end_price": 650.0,
      "total_return": 0.835010981187071,
      "cagr": 0.5009377479509596,
      "total_return_pct": 83.5011,
      "cagr_pct": 50.0938
    },
    {
      "ticker": "NESN.SW",
      "start_date": "2024-05-02",
      "end_date": "2025-10-29",
      "start_price": 88.636879,
      "end_price": 78.470001,
      "total_return": -0.11470256923570732,
      "cagr": -0.07840510970751913,
      "total_return_pct": -11.4703,
      "cagr_pct": -7.8405
    },
    {
      "ticker": "005930.KS",
      "start_date": "2024-05-02",
      "end_date": "2025-10-30",
      "start_price": 75779.609375,
      "end_price": 104400.0,
      "total_return": 0.3776793105830125,
      "cagr": 0.23903617669189914,
      "total_return_pct": 37.7679,
      "cagr_pct": 23.9036
    },
    {
      "ticker": "BAC",
      "start_date": "2024-05-01",
      "end_date": "2025-10-29",
      "start_price": 35.649784,
      "end_price": 52.580002,
      "total_return": 0.47490379467837407,
      "cagr": 0.2968671584555862,
      "total_return_pct": 47.4904,
      "cagr_pct": 29.6867
    },
    {
      "ticker": "WMT",
      "start_date": "2024-05-01",
      "end_date": "2025-10-29",
      "start_price": 57.9156,
      "end_price": 102.459999,
      "total_return": 0.7691260972451539,
      "cagr": 0.4646698419092268,
      "total_return_pct": 76.9126,
      "cagr_pct": 46.467
    },
    {
      "ticker": "AMD",
      "start_date": "2024-05-01",
      "end_date": "2025-10-29",
      "start_price": 144.270004,
      "end_price": 264.329987,
      "total_return": 0.8321894970839923,
      "cagr": 0.4993935257454618,
      "total_return_pct": 83.2189,
      "cagr_pct": 49.9394
    },
    {
      "ticker": "CRM",
      "start_date": "2024-05-01",
      "end_date": "2025-10-29",
      "start_price": 266.240387,
      "end_price": 251.460007,
      "total_return": -0.055515169646607965,
      "cagr": -0.037487149186719027,
      "total_return_pct": -5.5515,
      "cagr_pct": -3.7487
    },
    {
      "ticker": "PEP",
      "start_date": "2024-05-01",
      "end_date": "2025-10-29",
      "start_price": 166.047485,
      "end_price": 146.160004,
      "total_return": -0.11976984563991766,
      "cagr": -0.08179993028451704,
      "total_return_pct": -11.977,
      "cagr_pct": -8.18
    },
    {
      "ticker": "KO",
      "start_date": "2024-05-01",
      "end_date": "2025-10-29",
      "start_price": 59.252613,
      "end_price": 68.349998,
      "total_return": 0.1535355984403759,
      "cagr": 0.10026174535448207,
      "total_return_pct": 15.3536,
      "cagr_pct": 10.0262
    },
    {
      "ticker": "NFLX",
      "start_date": "2024-05-01",
      "end_date": "2025-10-29",
      "start_price": 551.710022,
      "end_price": 1100.410034,
      "total_return": 0.9945442177126624,
      "cagr": 0.5870193955714411,
      "total_return_pct": 99.4544,
      "cagr_pct": 58.7019
    },
    {
      "ticker": "SHEL.L",
      "start_date": "2024-05-01",
      "end_date": "2025-10-29",
      "start_price": 2817.304199,
      "end_price": 2875.5,
      "total_return": 0.020656555581533453,
      "cagr": 0.013771509135073856,
      "total_return_pct": 2.0657,
      "cagr_pct": 1.3772
    },
    {
      "ticker": "AZN.L",
      "start_date": "2024-05-01",
      "end_date": "2025-10-29",
      "start_price": 12166.665039,
      "end_price": 12560.0,
      "total_return": 0.03232890522379406,
      "cagr": 0.02151251874087934,
      "total_return_pct": 3.2329,
      "cagr_pct": 2.1513
    },
    {
      "ticker": "TMO",
      "start_date": "2024-05-01",
      "end_date": "2025-10-29",
      "start_price": 572.214844,
      "end_price": 558.309998,
      "total_return": -0.024300044543201782,
      "cagr": -0.016321760125206697,
      "total_return_pct": -2.43,
      "cagr_pct": -1.6322
    },
    {
      "ticker": "WFC",
      "start_date": "2024-05-01",
      "end_date": "2025-10-29",
      "start_price": 57.453186,
      "end_price": 86.0,
      "total_return": 0.4968708601708465,
      "cagr": 0.3097566707109485,
      "total_return_pct": 49.6871,
      "cagr_pct": 30.9757
    },
    {
      "ticker": "LIN",
      "start_date": "2024-05-01",
      "end_date": "2025-10-29",
      "start_price": 434.346313,
      "end_price": 432.01001,
      "total_return": -0.005378896144501488,
      "cagr": -0.003601456364653144,
      "total_return_pct": -0.5379,
      "cagr_pct": -0.3601
    },
    {
      "ticker": "ADBE",
      "start_date": "2024-05-01",
      "end_date": "2025-10-29",
      "start_price": 469.390015,
      "end_price": 337.859985,
      "total_return": -0.2802148004690471,
      "cagr": -0.19744459283321414,
      "total_return_pct": -28.0215,
      "cagr_pct": -19.7445
    },
    {
      "ticker": "MC.PA",
      "start_date": "2024-05-02",
      "end_date": "2025-10-29",
      "start_price": 748.48877,
      "end_price": 618.799988,
      "total_return": -0.17326750516176803,
      "cagr": -0.11972292245450156,
      "total_return_pct": -17.3268,
      "cagr_pct": -11.9723
    },
    {
      "ticker": "DIS",
      "start_date": "2024-05-01",
      "end_date": "2025-10-29",
      "start_price": 109.022591,
      "end_price": 110.239998,
      "total_return": 0.01116655932909949,
      "cagr": 0.00745619854841717,
      "total_return_pct": 1.1167,
      "cagr_pct": 0.7456
    },
    {
      "ticker": "NOVN.SW",
      "start_date": "2024-05-02",
      "end_date": "2025-10-29",
      "start_price": 85.801888,
      "end_price": 98.5,
      "total_return": 0.1479933933386537,
      "cagr": 0.09690846622906868,
      "total_return_pct": 14.7993,
      "cagr_pct": 9.6908
    },
    {
      "ticker": "MCD",
      "start_date": "2024-05-01",
      "end_date": "2025-10-29",
      "start_price": 264.899658,
      "end_price": 302.350006,
      "total_return": 0.1413755991775334,
      "cagr": 0.09248931532843163,
      "total_return_pct": 14.1376,
      "cagr_pct": 9.2489
    },
    {
      "ticker": "SAP.DE",
      "start_date": "2024-05-02",
      "end_date": "2025-10-29",
      "start_price": 164.943604,
      "end_price": 224.300003,
      "total_return": 0.35985875336178164,
      "cagr": 0.22875512162595646,
      "total_return_pct": 35.9859,
      "cagr_pct": 22.8755
    },
    {
      "ticker": "ACN",
      "start_date": "2024-05-01",
      "end_date": "2025-10-29",
      "start_price": 291.981812,
      "end_price": 247.75,
      "total_return": -0.15148824268420913,
      "cagr": -0.10406759014292655,
      "total_return_pct": -15.1488,
      "cagr_pct": -10.4068
    },
    {
      "ticker": "CSCO",
      "start_date": "2024-05-01",
      "end_date": "2025-10-29",
      "start_price": 44.931202,
      "end_price": 71.330002,
      "total_return": 0.5875382531395272,
      "cagr": 0.3623091260663005,
      "total_return_pct": 58.7538,
      "cagr_pct": 36.2309
    },
    {
      "ticker": "QCOM",
      "start_date": "2024-05-01",
      "end_date": "2025-10-29",
      "start_price": 159.020615,
      "end_price": 178.669998,
      "total_return": 0.12356500816815119,
      "cagr": 0.08105546160090249,
      "total_return_pct": 12.3565,
      "cagr_pct": 8.1055
    },
    {
      "ticker": "ABT",
      "start_date": "2024-05-01",
      "end_date": "2025-10-29",
      "start_price": 103.276215,
      "end_price": 124.43,
      "total_return": 0.20482727593742012,
      "cagr": 0.13275275727212477,
      "total_return_pct": 20.4827,
      "cagr_pct": 13.2753
    },
    {
      "ticker": "GE",
      "start_date": "2024-05-01",
      "end_date": "2025-10-29",
      "start_price": 158.215607,
      "end_price": 314.279999,
      "total_return": 0.9864032718097666,
      "cagr": 0.5826832399822115,
      "total_return_pct": 98.6403,
      "cagr_pct": 58.2683
    },
    {
      "ticker": "ORCL",
      "start_date": "2024-05-01",
      "end_date": "2025-10-29",
      "start_price": 112.927597,
      "end_price": 275.299988,
      "total_return": 1.437845088309773,
      "cagr": 0.8150561846708568,
      "total_return_pct": 143.7845,
      "cagr_pct": 81.5056
    },
    {
      "ticker": "INTU",
      "start_date": "2024-05-01",
      "end_date": "2025-10-29",
      "start_price": 609.294983,
      "end_price": 656.039978,
      "total_return": 0.0767198096625068,
      "cagr": 0.05069169006540464,
      "total_return_pct": 7.672,
      "cagr_pct": 5.0692
    },
    {
      "ticker": "CAT",
      "start_date": "2024-05-01",
      "end_date": "2025-10-29",
      "start_price": 323.659149,
      "end_price": 585.48999,
      "total_return": 0.8089709243071366,
      "cagr": 0.4866557525444215,
      "total_return_pct": 80.8971,
      "cagr_pct": 48.6656
    },
    {
      "ticker": "AMAT",
      "start_date": "2024-05-01",
      "end_date": "2025-10-29",
      "start_price": 191.276398,
      "end_price": 235.75,
      "total_return": 0.2325096186906137,
      "cagr": 0.1500976908110181,
      "total_return_pct": 23.251,
      "cagr_pct": 15.0098
    },
    {
      "ticker": "VZ",
      "start_date": "2024-05-01",
      "end_date": "2025-10-29",
      "start_price": 35.529789,
      "end_price": 40.209999,
      "total_return": 0.1317263695923554,
      "cagr": 0.08630219703417508,
      "total_return_pct": 13.1726,
      "cagr_pct": 8.6302
    },
    {
      "ticker": "HSBA.L",
      "start_date": "2024-05-01",
      "end_date": "2025-10-29",
      "start_price": 696.788025,
      "end_price": 1073.400024,
      "total_return": 0.54049723309252,
      "cagr": 0.3351710538804813,
      "total_return_pct": 54.0497,
      "cagr_pct": 33.5171
    },
    {
      "ticker": "DHR",
      "start_date": "2024-05-01",
      "end_date": "2025-10-29",
      "start_price": 244.899368,
      "end_price": 214.009995,
      "total_return": -0.12613088386249605,
      "cagr": -0.08624406801526607,
      "total_return_pct": -12.6131,
      "cagr_pct": -8.6244
    },
    {
      "ticker": "TXN",
      "start_date": "2024-05-01",
      "end_date": "2025-10-29",
      "start_price": 167.776154,
      "end_price": 160.259995,
      "total_return": -0.044798732703868804,
      "cagr": -0.03019513961421283,
      "total_return_pct": -4.4799,
      "cagr_pct": -3.0195
    },
    {
      "ticker": "9988.HK",
      "start_date": "2024-05-02",
      "end_date": "2025-10-30",
      "start_price": 75.733734,
      "end_price": 170.800003,
      "total_return": 1.2552697950511011,
      "cagr": 0.7229563443006124,
      "total_return_pct": 125.527,
      "cagr_pct": 72.2956
    },
    {
      "ticker": "IBM",
      "start_date": "2024-05-01",
      "end_date": "2025-10-29",
      "start_price": 156.967331,
      "end_price": 308.209991,
      "total_return": 0.9635295422547909,
      "cagr": 0.5704682707657125,
      "total_return_pct": 96.353,
      "cagr_pct": 57.0468
    },
    {
      "ticker": "COP",
      "start_date": "2024-05-01",
      "end_date": "2025-10-29",
      "start_price": 118.834824,
      "end_price": 88.080002,
      "total_return": -0.2588031087477476,
      "cagr": -0.18155162958732984,
      "total_return_pct": -25.8803,
      "cagr_pct": -18.1552
    },
    {
      "ticker": "CMCSA",
      "start_date": "2024-05-01",
      "end_date": "2025-10-29",
      "start_price": 36.238903,
      "end_price": 28.530001,
      "total_return": -0.21272449525574777,
      "cagr": -0.14785528613259658,
      "total_return_pct": -21.2724,
      "cagr_pct": -14.7855
    },
    {
      "ticker": "TTE.PA",
      "start_date": "2024-05-02",
      "end_date": "2025-10-29",
      "start_price": 61.347404,
      "end_price": 54.139999,
      "total_return": -0.1174850859857327,
      "cagr": -0.08034737128829317,
      "total_return_pct": -11.7485,
      "cagr_pct": -8.0347
    },
    {
      "ticker": "PM",
      "start_date": "2024-05-01",
      "end_date": "2025-10-29",
      "start_price": 90.386787,
      "end_price": 146.770004,
      "total_return": 0.6237993236701029,
      "cagr": 0.383046850812663,
      "total_return_pct": 62.3799,
      "cagr_pct": 38.3047
    },
    {
      "ticker": "AMGN",
      "start_date": "2024-05-01",
      "end_date": "2025-10-29",
      "start_price": 264.660065,
      "end_price": 291.769989,
      "total_return": 0.10243299965718755,
      "cagr": 0.06741121943781003,
      "total_return_pct": 10.2433,
      "cagr_pct": 6.7411
    },
    {
      "ticker": "RTX",
      "start_date": "2024-05-01",
      "end_date": "2025-10-29",
      "start_price": 98.113197,
      "end_price": 176.360001,
      "total_return": 0.7975155780845145,
      "cagr": 0.4803513942142621,
      "total_return_pct": 79.7516,
      "cagr_pct": 48.0351
    },
    {
      "ticker": "PFE",
      "start_date": "2024-05-01",
      "end_date": "2025-10-29",
      "start_price": 24.672352,
      "end_price": 24.290001,
      "total_return": -0.015497141259756764,
      "cagr": -0.010393683154164224,
      "total_return_pct": -1.5497,
      "cagr_pct": -1.0394
    },
    {
      "ticker": "UNP",
      "start_date": "2024-05-01",
      "end_date": "2025-10-29",
      "start_price": 226.993042,
      "end_price": 216.369995,
      "total_return": -0.046798997809658016,
      "cagr": -0.03155415775625792,
      "total_return_pct": -4.6799,
      "cagr_pct": -3.1554
    },
    {
      "ticker": "ROG.SW",
      "start_date": "2024-05-02",
      "end_date": "2025-10-29",
      "start_price": 207.245987,
      "end_price": 260.399994,
      "total_return": 0.25647785871862117,
      "cagr": 0.16533807495818986,
      "total_return_pct": 25.6478,
      "cagr_pct": 16.5338
    },
    {
      "ticker": "NOW",
      "start_date": "2024-05-01",
      "end_date": "2025-10-29",
      "start_price": 685.609985,
      "end_price": 911.700012,
      "total_return": 0.3297647812692457,
      "cagr": 0.21004053317205873,
      "total_return_pct": 32.9765,
      "cagr_pct": 21.0041
    },
    {
      "ticker": "SIE.DE",
      "start_date": "2024-05-02",
      "end_date": "2025-10-29",
      "start_price": 171.194534,
      "end_price": 245.75,
      "total_return": 0.43550143701916455,
      "cagr": 0.274152002657857,
      "total_return_pct": 43.5501,
      "cagr_pct": 27.4152
    },
    {
      "ticker": "BHP.AX",
      "start_date": "2024-05-01",
      "end_date": "2025-10-30",
      "start_price": 39.427185,
      "end_price": 43.880001,
      "total_return": 0.1129377104377105,
      "cagr": 0.07406392421804919,
      "total_return_pct": 11.2938,
      "cagr_pct": 7.4064
    },
    {
      "ticker": "NEE",
      "start_date": "2024-05-01",
      "end_date": "2025-10-29",
      "start_price": 65.685501,
      "end_price": 81.760002,
      "total_return": 0.24471916585458198,
      "cagr": 0.15770676768930714,
      "total_return_pct": 24.4719,
      "cagr_pct": 15.7707
    },
    {
      "ticker": "AXP",
      "start_date": "2024-05-01",
      "end_date": "2025-10-29",
      "start_price": 227.718109,
      "end_price": 358.220001,
      "total_return": 0.573085261369574,
      "cagr": 0.3539998457362372,
      "total_return_pct": 57.3085,
      "cagr_pct": 35.4
    },
    {
      "ticker": "RY.TO",
      "start_date": "2024-05-01",
      "end_date": "2025-10-29",
      "start_price": 127.297356,
      "end_price": 204.550003,
      "total_return": 0.606867652547159,
      "cagr": 0.3733829082357343,
      "total_return_pct": 60.6868,
      "cagr_pct": 37.3383
    },
    {
      "ticker": "GS",
      "start_date": "2024-05-01",
      "end_date": "2025-10-29",
      "start_price": 413.449615,
      "end_price": 783.059998,
      "total_return": 0.8939671685322548,
      "cagr": 0.5330276021977891,
      "total_return_pct": 89.3967,
      "cagr_pct": 53.3028
    },
    {
      "ticker": "SPGI",
      "start_date": "2024-05-01",
      "end_date": "2025-10-29",
      "start_price": 411.6138,
      "end_price": 473.049988,
      "total_return": 0.14925687072895188,
      "cagr": 0.09752997466944002,
      "total_return_pct": 14.9257,
      "cagr_pct": 9.753
    },
    {
      "ticker": "LOW",
      "start_date": "2024-05-01",
      "end_date": "2025-10-29",
      "start_price": 221.038162,
      "end_price": 238.490005,
      "total_return": 0.07895398281245769,
      "cagr": 0.05214962437110415,
      "total_return_pct": 7.8954,
      "cagr_pct": 5.215
    },
    {
      "ticker": "UBER",
      "start_date": "2024-05-01",
      "end_date": "2025-10-29",
      "start_price": 67.790001,
      "end_price": 95.760002,
      "total_return": 0.412597740713359,
      "cagr": 0.25995718413018243,
      "total_return_pct": 41.2598,
      "cagr_pct": 25.9957
    },
    {
      "ticker": "ISRG",
      "start_date": "2024-05-01",
      "end_date": "2025-10-29",
      "start_price": 371.700012,
      "end_price": 537.590027,
      "total_return": 0.4463008049513846,
      "cagr": 0.2799882346642659,
      "total_return_pct": 44.6301,
      "cagr_pct": 27.9988
    },
    {
      "ticker": "INTC",
      "start_date": "2024-05-01",
      "end_date": "2025-10-29",
      "start_price": 30.056479,
      "end_price": 41.34,
      "total_return": 0.375410634086232,
      "cagr": 0.23767088813316906,
      "total_return_pct": 37.5411,
      "cagr_pct": 23.7671
    },
    {
      "ticker": "ULVR.L",
      "start_date": "2024-05-01",
      "end_date": "2025-10-29",
      "start_price": 4137.94043,
      "end_price": 4610.0,
      "total_return": 0.11408080380416452,
      "cagr": 0.07494242623359959,
      "total_return_pct": 11.4081,
      "cagr_pct": 7.4942
    },
    {
      "ticker": "HON",
      "start_date": "2024-05-01",
      "end_date": "2025-10-29",
      "start_price": 189.286621,
      "end_price": 212.889999,
      "total_return": 0.12469649550249051,
      "cagr": 0.08178361802085421,
      "total_return_pct": 12.4696,
      "cagr_pct": 8.1784
    },
    {
      "ticker": "ETN",
      "start_date": "2024-05-01",
      "end_date": "2025-10-29",
      "start_price": 306.097534,
      "end_price": 387.75,
      "total_return": 0.2667530989399618,
      "cagr": 0.17137625885209484,
      "total_return_pct": 26.6753,
      "cagr_pct": 17.1376
    },
    {
      "ticker": "ELV",
      "start_date": "2024-05-01",
      "end_date": "2025-10-29",
      "start_price": 512.322388,
      "end_price": 336.359985,
      "total_return": -0.34346030267253924,
      "cagr": -0.24533252113352244,
      "total_return_pct": -34.346,
      "cagr_pct": -24.5333
    },
    {
      "ticker": "MU",
      "start_date": "2024-05-01",
      "end_date": "2025-10-29",
      "start_price": 109.025673,
      "end_price": 226.630005,
      "total_return": 1.0786847613817931,
      "cagr": 0.6314983025591003,
      "total_return_pct": 107.8685,
      "cagr_pct": 63.1498
    },
    {
      "ticker": "CBA.AX",
      "start_date": "2024-05-01",
      "end_date": "2025-10-30",
      "start_price": 108.654655,
      "end_price": 170.529999,
      "total_return": 0.5694679446800262,
      "cagr": 0.35117122631532927,
      "total_return_pct": 56.9468,
      "cagr_pct": 35.1171
    },
    {
      "ticker": "SU.PA",
      "start_date": "2024-05-02",
      "end_date": "2025-10-29",
      "start_price": 206.644348,
      "end_price": 257.399994,
      "total_return": 0.24561835931004317,
      "cagr": 0.15857846633636097,
      "total_return_pct": 24.5618,
      "cagr_pct": 15.8578
    },
    {
      "ticker": "PGR",
      "start_date": "2024-05-01",
      "end_date": "2025-10-29",
      "start_price": 207.38176,
      "end_price": 207.970001,
      "total_return": 0.002836515507243842,
      "cagr": 0.0018966144227343662,
      "total_return_pct": 0.2837,
      "cagr_pct": 0.1897
    },
    {
      "ticker": "T",
      "start_date": "2024-05-01",
      "end_date": "2025-10-29",
      "start_price": 15.752812,
      "end_price": 25.139999,
      "total_return": 0.5959054659150753,
      "cagr": 0.36710813662289943,
      "total_return_pct": 59.5905,
      "cagr_pct": 36.7108
    },
    {
      "ticker": "BKNG",
      "start_date": "2024-05-01",
      "end_date": "2025-10-29",
      "start_price": 3375.697266,
      "end_price": 5075.859863,
      "total_return": 0.5036478285446815,
      "cagr": 0.3137204950611596,
      "total_return_pct": 50.3648,
      "cagr_pct": 31.372
    },
    {
      "ticker": "SYK",
      "start_date": "2024-05-01",
      "end_date": "2025-10-29",
      "start_price": 323.683258,
      "end_price": 369.589996,
      "total_return": 0.14182611283904234,
      "cagr": 0.09277776217249656,
      "total_return_pct": 14.1826,
      "cagr_pct": 9.2778
    },
    {
      "ticker": "LRCX",
      "start_date": "2024-05-01",
      "end_date": "2025-10-29",
      "start_price": 85.479729,
      "end_price": 160.669998,
      "total_return": 0.8796269082137547,
      "cagr": 0.52525300457292,
      "total_return_pct": 87.9627,
      "cagr_pct": 52.5253
    },
    {
      "ticker": "C",
      "start_date": "2024-05-01",
      "end_date": "2025-10-29",
      "start_price": 58.44698,
      "end_price": 99.120003,
      "total_return": 0.6958960677869859,
      "cagr": 0.42382955502538344,
      "total_return_pct": 69.5896,
      "cagr_pct": 42.383
    },
    {
      "ticker": "BRK-A",
      "start_date": "2024-05-01",
      "end_date": "2025-10-29",
      "start_price": 602100.0,
      "end_price": 712900.0,
      "total_return": 0.18402258761003165,
      "cagr": 0.11963020713125894,
      "total_return_pct": 18.4023,
      "cagr_pct": 11.963
    },
    {
      "ticker": "BLK",
      "start_date": "2024-05-01",
      "end_date": "2025-10-29",
      "start_price": 727.292969,
      "end_price": 1098.0,
      "total_return": 0.5097079817602732,
      "cagr": 0.317260050600791,
      "total_return_pct": 50.9708,
      "cagr_pct": 31.726
    },
    {
      "ticker": "8306.T",
      "start_date": "2024-05-01",
      "end_date": "2025-10-30",
      "start_price": 1487.532959,
      "end_price": 2323.0,
      "total_return": 0.5616460704077755,
      "cagr": 0.3466710254415075,
      "total_return_pct": 56.1646,
      "cagr_pct": 34.6671
    },
    {
      "ticker": "TSM",
      "start_date": "2024-05-01",
      "end_date": "2025-10-29",
      "start_price": 132.176422,
      "end_price": 305.089996,
      "total_return": 1.3082028658854896,
      "cagr": 0.7499043945563693,
      "total_return_pct": 130.8203,
      "cagr_pct": 74.9904
    }
  ],
  "ranking": [
    {
      "ticker": "AVGO",
      "start_date": "2024-05-01",
      "end_date": "2025-10-29",
      "start_price": 122.287102,
      "end_price": 385.980011,
      "total_return": 2.1563427824897223,
      "cagr": 1.1574078876113352,
      "total_return_pct": 215.6343,
      "cagr_pct": 115.7408
    },
    {
      "ticker": "TSLA",
      "start_date": "2024-05-01",
      "end_date": "2025-10-29",
      "start_price": 179.990005,
      "end_price": 461.51001,
      "total_return": 1.5640868697187353,
      "cagr": 0.8774052347485926,
      "total_return_pct": 156.4087,
      "cagr_pct": 87.7405
    },
    {
      "ticker": "NVDA",
      "start_date": "2024-05-01",
      "end_date": "2025-10-29",
      "start_price": 83.003265,
      "end_price": 207.039993,
      "total_return": 1.4943596174937523,
      "cagr": 0.8430968929259186,
      "total_return_pct": 149.436,
      "cagr_pct": 84.3097
    },
    {
      "ticker": "ORCL",
      "start_date": "2024-05-01",
      "end_date": "2025-10-29",
      "start_price": 112.927597,
      "end_price": 275.299988,
      "total_return": 1.437845088309773,
      "cagr": 0.8150561846708568,
      "total_return_pct": 143.7845,
      "cagr_pct": 81.5056
    },
    {
      "ticker": "TSM",
      "start_date": "2024-05-01",
      "end_date": "2025-10-29",
      "start_price": 132.176422,
      "end_price": 305.089996,
      "total_return": 1.3082028658854896,
      "cagr": 0.7499043945563693,
      "total_return_pct": 130.8203,
      "cagr_pct": 74.9904
    },
    {
      "ticker": "9988.HK",
      "start_date": "2024-05-02",
      "end_date": "2025-10-30",
      "start_price": 75.733734,
      "end_price": 170.800003,
      "total_return": 1.2552697950511011,
      "cagr": 0.7229563443006124,
      "total_return_pct": 125.527,
      "cagr_pct": 72.2956
    },
    {
      "ticker": "MU",
      "start_date": "2024-05-01",
      "end_date": "2025-10-29",
      "start_price": 109.025673,
      "end_price": 226.630005,
      "total_return": 1.0786847613817931,
      "cagr": 0.6314983025591003,
      "total_return_pct": 107.8685,
      "cagr_pct": 63.1498
    },
    {
      "ticker": "2330.TW",
      "start_date": "2024-05-02",
      "end_date": "2025-10-30",
      "start_price": 752.925476,
      "end_price": 1505.0,
      "total_return": 0.9988698056109426,
      "cagr": 0.5893209725913768,
      "total_return_pct": 99.887,
      "cagr_pct": 58.9321
    },
    {
      "ticker": "NFLX",
      "start_date": "2024-05-01",
      "end_date": "2025-10-29",
      "start_price": 551.710022,
      "end_price": 1100.410034,
      "total_return": 0.9945442177126624,
      "cagr": 0.5870193955714411,
      "total_return_pct": 99.4544,
      "cagr_pct": 58.7019
    },
    {
      "ticker": "GE",
      "start_date": "2024-05-01",
      "end_date": "2025-10-29",
      "start_price": 158.215607,
      "end_price": 314.279999,
      "total_return": 0.9864032718097666,
      "cagr": 0.5826832399822115,
      "total_return_pct": 98.6403,
      "cagr_pct": 58.2683
    },
    {
      "ticker": "IBM",
      "start_date": "2024-05-01",
      "end_date": "2025-10-29",
      "start_price": 156.967331,
      "end_price": 308.209991,
      "total_return": 0.9635295422547909,
      "cagr": 0.5704682707657125,
      "total_return_pct": 96.353,
      "cagr_pct": 57.0468
    },
    {
      "ticker": "GS",
      "start_date": "2024-05-01",
      "end_date": "2025-10-29",
      "start_price": 413.449615,
      "end_price": 783.059998,
      "total_return": 0.8939671685322548,
      "cagr": 0.5330276021977891,
      "total_return_pct": 89.3967,
      "cagr_pct": 53.3028
    },
    {
      "ticker": "LRCX",
      "start_date": "2024-05-01",
      "end_date": "2025-10-29",
      "start_price": 85.479729,
      "end_price": 160.669998,
      "total_return": 0.8796269082137547,
      "cagr": 0.52525300457292,
      "total_return_pct": 87.9627,
      "cagr_pct": 52.5253
    },
    {
      "ticker": "0700.HK",
      "start_date": "2024-05-02",
      "end_date": "2025-10-30",
      "start_price": 354.221313,
      "end_price": 650.0,
      "total_return": 0.835010981187071,
      "cagr": 0.5009377479509596,
      "total_return_pct": 83.5011,
      "cagr_pct": 50.0938
    },
    {
      "ticker": "AMD",
      "start_date": "2024-05-01",
      "end_date": "2025-10-29",
      "start_price": 144.270004,
      "end_price": 264.329987,
      "total_return": 0.8321894970839923,
      "cagr": 0.4993935257454618,
      "total_return_pct": 83.2189,
      "cagr_pct": 49.9394
    },
    {
      "ticker": "CAT",
      "start_date": "2024-05-01",
      "end_date": "2025-10-29",
      "start_price": 323.659149,
      "end_price": 585.48999,
      "total_return": 0.8089709243071366,
      "cagr": 0.4866557525444215,
      "total_return_pct": 80.8971,
      "cagr_pct": 48.6656
    },
    {
      "ticker": "RTX",
      "start_date": "2024-05-01",
      "end_date": "2025-10-29",
      "start_price": 98.113197,
      "end_price": 176.360001,
      "total_return": 0.7975155780845145,
      "cagr": 0.4803513942142621,
      "total_return_pct": 79.7516,
      "cagr_pct": 48.0351
    },
    {
      "ticker": "WMT",
      "start_date": "2024-05-01",
      "end_date": "2025-10-29",
      "start_price": 57.9156,
      "end_price": 102.459999,
      "total_return": 0.7691260972451539,
      "cagr": 0.4646698419092268,
      "total_return_pct": 76.9126,
      "cagr_pct": 46.467
    },
    {
      "ticker": "META",
      "start_date": "2024-05-01",
      "end_date": "2025-10-29",
      "start_price": 436.96225,
      "end_price": 751.669983,
      "total_return": 0.7202172117388428,
      "cagr": 0.43745700907319374,
      "total_return_pct": 72.0217,
      "cagr_pct": 43.7457
    },
    {
      "ticker": "C",
      "start_date": "2024-05-01",
      "end_date": "2025-10-29",
      "start_price": 58.44698,
      "end_price": 99.120003,
      "total_return": 0.6958960677869859,
      "cagr": 0.42382955502538344,
      "total_return_pct": 69.5896,
      "cagr_pct": 42.383
    },
    {
      "ticker": "GOOGL",
      "start_date": "2024-05-01",
      "end_date": "2025-10-29",
      "start_price": 162.737579,
      "end_price": 274.570007,
      "total_return": 0.6871948595287276,
      "cagr": 0.4189384676024923,
      "total_return_pct": 68.7195,
      "cagr_pct": 41.8938
    },
    {
      "ticker": "GOOG",
      "start_date": "2024-05-01",
      "end_date": "2025-10-29",
      "start_price": 164.444672,
      "end_price": 275.170013,
      "total_return": 0.6733288509671389,
      "cagr": 0.41112686923940234,
      "total_return_pct": 67.3329,
      "cagr_pct": 41.1127
    },
    {
      "ticker": "JPM",
      "start_date": "2024-05-01",
      "end_date": "2025-10-29",
      "start_price": 185.709351,
      "end_price": 305.51001,
      "total_return": 0.6450976151803913,
      "cagr": 0.39515585545775744,
      "total_return_pct": 64.5098,
      "cagr_pct": 39.5156
    },
    {
      "ticker": "PM",
      "start_date": "2024-05-01",
      "end_date": "2025-10-29",
      "start_price": 90.386787,
      "end_price": 146.770004,
      "total_return": 0.6237993236701029,
      "cagr": 0.383046850812663,
      "total_return_pct": 62.3799,
      "cagr_pct": 38.3047
    },
    {
      "ticker": "RY.TO",
      "start_date": "2024-05-01",
      "end_date": "2025-10-29",
      "start_price": 127.297356,
      "end_price": 204.550003,
      "total_return": 0.606867652547159,
      "cagr": 0.3733829082357343,
      "total_return_pct": 60.6868,
      "cagr_pct": 37.3383
    },
    {
      "ticker": "AAPL",
      "start_date": "2024-05-01",
      "end_date": "2025-10-29",
      "start_price": 168.092896,
      "end_price": 269.700012,
      "total_return": 0.6044700246983152,
      "cagr": 0.3720117164428727,
      "total_return_pct": 60.447,
      "cagr_pct": 37.2012
    },
    {
      "ticker": "T",
      "start_date": "2024-05-01",
      "end_date": "2025-10-29",
      "start_price": 15.752812,
      "end_price": 25.139999,
      "total_return": 0.5959054659150753,
      "cagr": 0.36710813662289943,
      "total_return_pct": 59.5905,
      "cagr_pct": 36.7108
    },
    {
      "ticker": "CSCO",
      "start_date": "2024-05-01",
      "end_date": "2025-10-29",
      "start_price": 44.931202,
      "end_price": 71.330002,
      "total_return": 0.5875382531395272,
      "cagr": 0.3623091260663005,
      "total_return_pct": 58.7538,
      "cagr_pct": 36.2309
    },
    {
      "ticker": "AXP",
      "start_date": "2024-05-01",
      "end_date": "2025-10-29",
      "start_price": 227.718109,
      "end_price": 358.220001,
      "total_return": 0.573085261369574,
      "cagr": 0.3539998457362372,
      "total_return_pct": 57.3085,
      "cagr_pct": 35.4
    },
    {
      "ticker": "CBA.AX",
      "start_date": "2024-05-01",
      "end_date": "2025-10-30",
      "start_price": 108.654655,
      "end_price": 170.529999,
      "total_return": 0.5694679446800262,
      "cagr": 0.35117122631532927,
      "total_return_pct": 56.9468,
      "cagr_pct": 35.1171
    },
    {
      "ticker": "8306.T",
      "start_date": "2024-05-01",
      "end_date": "2025-10-30",
      "start_price": 1487.532959,
      "end_price": 2323.0,
      "total_return": 0.5616460704077755,
      "cagr": 0.3466710254415075,
      "total_return_pct": 56.1646,
      "cagr_pct": 34.6671
    },
    {
      "ticker": "HSBA.L",
      "start_date": "2024-05-01",
      "end_date": "2025-10-29",
      "start_price": 696.788025,
      "end_price": 1073.400024,
      "total_return": 0.54049723309252,
      "cagr": 0.3351710538804813,
      "total_return_pct": 54.0497,
      "cagr_pct": 33.5171
    },
    {
      "ticker": "BLK",
      "start_date": "2024-05-01",
      "end_date": "2025-10-29",
      "start_price": 727.292969,
      "end_price": 1098.0,
      "total_return": 0.5097079817602732,
      "cagr": 0.317260050600791,
      "total_return_pct": 50.9708,
      "cagr_pct": 31.726
    },
    {
      "ticker": "BKNG",
      "start_date": "2024-05-01",
      "end_date": "2025-10-29",
      "start_price": 3375.697266,
      "end_price": 5075.859863,
      "total_return": 0.5036478285446815,
      "cagr": 0.3137204950611596,
      "total_return_pct": 50.3648,
      "cagr_pct": 31.372
    },
    {
      "ticker": "WFC",
      "start_date": "2024-05-01",
      "end_date": "2025-10-29",
      "start_price": 57.453186,
      "end_price": 86.0,
      "total_return": 0.4968708601708465,
      "cagr": 0.3097566707109485,
      "total_return_pct": 49.6871,
      "cagr_pct": 30.9757
    },
    {
      "ticker": "BAC",
      "start_date": "2024-05-01",
      "end_date": "2025-10-29",
      "start_price": 35.649784,
      "end_price": 52.580002,
      "total_return": 0.47490379467837407,
      "cagr": 0.2968671584555862,
      "total_return_pct": 47.4904,
      "cagr_pct": 29.6867
    },
    {
      "ticker": "ABBV",
      "start_date": "2024-05-01",
      "end_date": "2025-10-29",
      "start_price": 153.607407,
      "end_price": 225.139999,
      "total_return": 0.46568452882068456,
      "cagr": 0.2914387055442995,
      "total_return_pct": 46.5685,
      "cagr_pct": 29.1439
    },
    {
      "ticker": "ISRG",
      "start_date": "2024-05-01",
      "end_date": "2025-10-29",
      "start_price": 371.700012,
      "end_price": 537.590027,
      "total_return": 0.4463008049513846,
      "cagr": 0.2799882346642659,
      "total_return_pct": 44.6301,
      "cagr_pct": 27.9988
    },
    {
      "ticker": "SIE.DE",
      "start_date": "2024-05-02",
      "end_date": "2025-10-29",
      "start_price": 171.194534,
      "end_price": 245.75,
      "total_return": 0.43550143701916455,
      "cagr": 0.274152002657857,
      "total_return_pct": 43.5501,
      "cagr_pct": 27.4152
    },
    {
      "ticker": "UBER",
      "start_date": "2024-05-01",
      "end_date": "2025-10-29",
      "start_price": 67.790001,
      "end_price": 95.760002,
      "total_return": 0.412597740713359,
      "cagr": 0.25995718413018243,
      "total_return_pct": 41.2598,
      "cagr_pct": 25.9957
    },
    {
      "ticker": "MSFT",
      "start_date": "2024-05-01",
      "end_date": "2025-10-29",
      "start_price": 390.58728,
      "end_price": 541.549988,
      "total_return": 0.38650185283516447,
      "cagr": 0.2443385205980697,
      "total_return_pct": 38.6502,
      "cagr_pct": 24.4339
    },
    {
      "ticker": "005930.KS",
      "start_date": "2024-05-02",
      "end_date": "2025-10-30",
      "start_price": 75779.609375,
      "end_price": 104400.0,
      "total_return": 0.3776793105830125,
      "cagr": 0.23903617669189914,
      "total_return_pct": 37.7679,
      "cagr_pct": 23.9036
    },
    {
      "ticker": "INTC",
      "start_date": "2024-05-01",
      "end_date": "2025-10-29",
      "start_price": 30.056479,
      "end_price": 41.34,
      "total_return": 0.375410634086232,
      "cagr": 0.23767088813316906,
      "total_return_pct": 37.5411,
      "cagr_pct": 23.7671
    },
    {
      "ticker": "VT",
      "start_date": "2024-05-01",
      "end_date": "2025-10-29",
      "start_price": 103.444954,
      "end_price": 141.589996,
      "total_return": 0.3687472513110919,
      "cagr": 0.23365654944177017,
      "total_return_pct": 36.8747,
      "cagr_pct": 23.3657
    },
    {
      "ticker": "SAP.DE",
      "start_date": "2024-05-02",
      "end_date": "2025-10-29",
      "start_price": 164.943604,
      "end_price": 224.300003,
      "total_return": 0.35985875336178164,
      "cagr": 0.22875512162595646,
      "total_return_pct": 35.9859,
      "cagr_pct": 22.8755
    },
    {
      "ticker": "NOW",
      "start_date": "2024-05-01",
      "end_date": "2025-10-29",
      "start_price": 685.609985,
      "end_price": 911.700012,
      "total_return": 0.3297647812692457,
      "cagr": 0.21004053317205873,
      "total_return_pct": 32.9765,
      "cagr_pct": 21.0041
    },
    {
      "ticker": "JNJ",
      "start_date": "2024-05-01",
      "end_date": "2025-10-29",
      "start_price": 144.177399,
      "end_price": 186.600006,
      "total_return": 0.2942389570750179,
      "cagr": 0.18831821840252805,
      "total_return_pct": 29.4239,
      "cagr_pct": 18.8318
    },
    {
      "ticker": "V",
      "start_date": "2024-05-01",
      "end_date": "2025-10-29",
      "start_price": 264.43515,
      "end_price": 341.279999,
      "total_return": 0.29059997731105014,
      "cagr": 0.1860820843601445,
      "total_return_pct": 29.06,
      "cagr_pct": 18.6082
    },
    {
      "ticker": "AMZN",
      "start_date": "2024-05-01",
      "end_date": "2025-10-29",
      "start_price": 179.0,
      "end_price": 230.300003,
      "total_return": 0.28659219581987605,
      "cagr": 0.18361690688670396,
      "total_return_pct": 28.6592,
      "cagr_pct": 18.3617
    },
    {
      "ticker": "ASML",
      "start_date": "2024-05-01",
      "end_date": "2025-10-29",
      "start_price": 841.258301,
      "end_price": 1070.839966,
      "total_return": 0.2729027039921714,
      "cagr": 0.17517728522660736,
      "total_return_pct": 27.2903,
      "cagr_pct": 17.5177
    },
    {
      "ticker": "COST",
      "start_date": "2024-05-01",
      "end_date": "2025-10-29",
      "start_price": 717.511047,
      "end_price": 912.419983,
      "total_return": 0.2716459018479629,
      "cagr": 0.174400960041319,
      "total_return_pct": 27.1646,
      "cagr_pct": 17.4401
    },
    {
      "ticker": "ETN",
      "start_date": "2024-05-01",
      "end_date": "2025-10-29",
      "start_price": 306.097534,
      "end_price": 387.75,
      "total_return": 0.2667530989399618,
      "cagr": 0.17137625885209484,
      "total_return_pct": 26.6753,
      "cagr_pct": 17.1376
    },
    {
      "ticker": "MA",
      "start_date": "2024-05-01",
      "end_date": "2025-10-29",
      "start_price": 438.311707,
      "end_price": 554.580017,
      "total_return": 0.2652639863623558,
      "cagr": 0.170454931222207,
      "total_return_pct": 26.5264,
      "cagr_pct": 17.0455
    },
    {
      "ticker": "ROG.SW",
      "start_date": "2024-05-02",
      "end_date": "2025-10-29",
      "start_price": 207.245987,
      "end_price": 260.399994,
      "total_return": 0.25647785871862117,
      "cagr": 0.16533807495818986,
      "total_return_pct": 25.6478,
      "cagr_pct": 16.5338
    },
    {
      "ticker": "SU.PA",
      "start_date": "2024-05-02",
      "end_date": "2025-10-29",
      "start_price": 206.644348,
      "end_price": 257.399994,
      "total_return": 0.24561835931004317,
      "cagr": 0.15857846633636097,
      "total_return_pct": 24.5618,
      "cagr_pct": 15.8578
    },
    {
      "ticker": "NEE",
      "start_date": "2024-05-01",
      "end_date": "2025-10-29",
      "start_price": 65.685501,
      "end_price": 81.760002,
      "total_return": 0.24471916585458198,
      "cagr": 0.15770676768930714,
      "total_return_pct": 24.4719,
      "cagr_pct": 15.7707
    },
    {
      "ticker": "AMAT",
      "start_date": "2024-05-01",
      "end_date": "2025-10-29",
      "start_price": 191.276398,
      "end_price": 235.75,
      "total_return": 0.2325096186906137,
      "cagr": 0.1500976908110181,
      "total_return_pct": 23.251,
      "cagr_pct": 15.0098
    },
    {
      "ticker": "ABT",
      "start_date": "2024-05-01",
      "end_date": "2025-10-29",
      "start_price": 103.276215,
      "end_price": 124.43,
      "total_return": 0.20482727593742012,
      "cagr": 0.13275275727212477,
      "total_return_pct": 20.4827,
      "cagr_pct": 13.2753
    },
    {
      "ticker": "BRK-B",
      "start_date": "2024-05-01",
      "end_date": "2025-10-29",
      "start_price": 398.579987,
      "end_price": 475.76001,
      "total_return": 0.1936374775289076,
      "cagr": 0.12570420275524885,
      "total_return_pct": 19.3637,
      "cagr_pct": 12.5704
    },
    {
      "ticker": "BRK-A",
      "start_date": "2024-05-01",
      "end_date": "2025-10-29",
      "start_price": 602100.0,
      "end_price": 712900.0,
      "total_return": 0.18402258761003165,
      "cagr": 0.11963020713125894,
      "total_return_pct": 18.4023,
      "cagr_pct": 11.963
    },
    {
      "ticker": "HD",
      "start_date": "2024-05-01",
      "end_date": "2025-10-29",
      "start_price": 320.099121,
      "end_price": 378.040009,
      "total_return": 0.18100920506495943,
      "cagr": 0.11772321198009594,
      "total_return_pct": 18.1009,
      "cagr_pct": 11.7723
    },
    {
      "ticker": "KO",
      "start_date": "2024-05-01",
      "end_date": "2025-10-29",
      "start_price": 59.252613,
      "end_price": 68.349998,
      "total_return": 0.1535355984403759,
      "cagr": 0.10026174535448207,
      "total_return_pct": 15.3536,
      "cagr_pct": 10.0262
    },
    {
      "ticker": "SPGI",
      "start_date": "2024-05-01",
      "end_date": "2025-10-29",
      "start_price": 411.6138,
      "end_price": 473.049988,
      "total_return": 0.14925687072895188,
      "cagr": 0.09752997466944002,
      "total_return_pct": 14.9257,
      "cagr_pct": 9.753
    },
    {
      "ticker": "NOVN.SW",
      "start_date": "2024-05-02",
      "end_date": "2025-10-29",
      "start_price": 85.801888,
      "end_price": 98.5,
      "total_return": 0.1479933933386537,
      "cagr": 0.09690846622906868,
      "total_return_pct": 14.7993,
      "cagr_pct": 9.6908
    },
    {
      "ticker": "SYK",
      "start_date": "2024-05-01",
      "end_date": "2025-10-29",
      "start_price": 323.683258,
      "end_price": 369.589996,
      "total_return": 0.14182611283904234,
      "cagr": 0.09277776217249656,
      "total_return_pct": 14.1826,
      "cagr_pct": 9.2778
    },
    {
      "ticker": "MCD",
      "start_date": "2024-05-01",
      "end_date": "2025-10-29",
      "start_price": 264.899658,
      "end_price": 302.350006,
      "total_return": 0.1413755991775334,
      "cagr": 0.09248931532843163,
      "total_return_pct": 14.1376,
      "cagr_pct": 9.2489
    },
    {
      "ticker": "VZ",
      "start_date": "2024-05-01",
      "end_date": "2025-10-29",
      "start_price": 35.529789,
      "end_price": 40.209999,
      "total_return": 0.1317263695923554,
      "cagr": 0.08630219703417508,
      "total_return_pct": 13.1726,
      "cagr_pct": 8.6302
    },
    {
      "ticker": "HON",
      "start_date": "2024-05-01",
      "end_date": "2025-10-29",
      "start_price": 189.286621,
      "end_price": 212.889999,
      "total_return": 0.12469649550249051,
      "cagr": 0.08178361802085421,
      "total_return_pct": 12.4696,
      "cagr_pct": 8.1784
    },
    {
      "ticker": "QCOM",
      "start_date": "2024-05-01",
      "end_date": "2025-10-29",
      "start_price": 159.020615,
      "end_price": 178.669998,
      "total_return": 0.12356500816815119,
      "cagr": 0.08105546160090249,
      "total_return_pct": 12.3565,
      "cagr_pct": 8.1055
    },
    {
      "ticker": "ULVR.L",
      "start_date": "2024-05-01",
      "end_date": "2025-10-29",
      "start_price": 4137.94043,
      "end_price": 4610.0,
      "total_return": 0.11408080380416452,
      "cagr": 0.07494242623359959,
      "total_return_pct": 11.4081,
      "cagr_pct": 7.4942
    },
    {
      "ticker": "BHP.AX",
      "start_date": "2024-05-01",
      "end_date": "2025-10-30",
      "start_price": 39.427185,
      "end_price": 43.880001,
      "total_return": 0.1129377104377105,
      "cagr": 0.07406392421804919,
      "total_return_pct": 11.2938,
      "cagr_pct": 7.4064
    },
    {
      "ticker": "AMGN",
      "start_date": "2024-05-01",
      "end_date": "2025-10-29",
      "start_price": 264.660065,
      "end_price": 291.769989,
      "total_return": 0.10243299965718755,
      "cagr": 0.06741121943781003,
      "total_return_pct": 10.2433,
      "cagr_pct": 6.7411
    },
    {
      "ticker": "LOW",
      "start_date": "2024-05-01",
      "end_date": "2025-10-29",
      "start_price": 221.038162,
      "end_price": 238.490005,
      "total_return": 0.07895398281245769,
      "cagr": 0.05214962437110415,
      "total_return_pct": 7.8954,
      "cagr_pct": 5.215
    },
    {
      "ticker": "INTU",
      "start_date": "2024-05-01",
      "end_date": "2025-10-29",
      "start_price": 609.294983,
      "end_price": 656.039978,
      "total_return": 0.0767198096625068,
      "cagr": 0.05069169006540464,
      "total_return_pct": 7.672,
      "cagr_pct": 5.0692
    },
    {
      "ticker": "LLY",
      "start_date": "2024-05-01",
      "end_date": "2025-10-29",
      "start_price": 768.46936,
      "end_price": 813.530029,
      "total_return": 0.058636910292295896,
      "cagr": 0.03885438340345648,
      "total_return_pct": 5.8637,
      "cagr_pct": 3.8854
    },
    {
      "ticker": "XOM",
      "start_date": "2024-05-01",
      "end_date": "2025-10-29",
      "start_price": 110.191711,
      "end_price": 116.449997,
      "total_return": 0.05679452148881592,
      "cagr": 0.03764458865282316,
      "total_return_pct": 5.6795,
      "cagr_pct": 3.7645
    },
    {
      "ticker": "CVX",
      "start_date": "2024-05-01",
      "end_date": "2025-10-29",
      "start_price": 149.504196,
      "end_price": 155.100006,
      "total_return": 0.03742911623880496,
      "cagr": 0.024885833103254207,
      "total_return_pct": 3.7429,
      "cagr_pct": 2.4886
    },
    {
      "ticker": "AZN.L",
      "start_date": "2024-05-01",
      "end_date": "2025-10-29",
      "start_price": 12166.665039,
      "end_price": 12560.0,
      "total_return": 0.03232890522379406,
      "cagr": 0.02151251874087934,
      "total_return_pct": 3.2329,
      "cagr_pct": 2.1513
    },
    {
      "ticker": "SHEL.L",
      "start_date": "2024-05-01",
      "end_date": "2025-10-29",
      "start_price": 2817.304199,
      "end_price": 2875.5,
      "total_return": 0.020656555581533453,
      "cagr": 0.013771509135073856,
      "total_return_pct": 2.0657,
      "cagr_pct": 1.3772
    },
    {
      "ticker": "DIS",
      "start_date": "2024-05-01",
      "end_date": "2025-10-29",
      "start_price": 109.022591,
      "end_price": 110.239998,
      "total_return": 0.01116655932909949,
      "cagr": 0.00745619854841717,
      "total_return_pct": 1.1167,
      "cagr_pct": 0.7456
    },
    {
      "ticker": "PGR",
      "start_date": "2024-05-01",
      "end_date": "2025-10-29",
      "start_price": 207.38176,
      "end_price": 207.970001,
      "total_return": 0.002836515507243842,
      "cagr": 0.0018966144227343662,
      "total_return_pct": 0.2837,
      "cagr_pct": 0.1897
    },
    {
      "ticker": "LIN",
      "start_date": "2024-05-01",
      "end_date": "2025-10-29",
      "start_price": 434.346313,
      "end_price": 432.01001,
      "total_return": -0.005378896144501488,
      "cagr": -0.003601456364653144,
      "total_return_pct": -0.5379,
      "cagr_pct": -0.3601
    },
    {
      "ticker": "PFE",
      "start_date": "2024-05-01",
      "end_date": "2025-10-29",
      "start_price": 24.672352,
      "end_price": 24.290001,
      "total_return": -0.015497141259756764,
      "cagr": -0.010393683154164224,
      "total_return_pct": -1.5497,
      "cagr_pct": -1.0394
    },
    {
      "ticker": "TMO",
      "start_date": "2024-05-01",
      "end_date": "2025-10-29",
      "start_price": 572.214844,
      "end_price": 558.309998,
      "total_return": -0.024300044543201782,
      "cagr": -0.016321760125206697,
      "total_return_pct": -2.43,
      "cagr_pct": -1.6322
    },
    {
      "ticker": "TXN",
      "start_date": "2024-05-01",
      "end_date": "2025-10-29",
      "start_price": 167.776154,
      "end_price": 160.259995,
      "total_return": -0.044798732703868804,
      "cagr": -0.03019513961421283,
      "total_return_pct": -4.4799,
      "cagr_pct": -3.0195
    },
    {
      "ticker": "UNP",
      "start_date": "2024-05-01",
      "end_date": "2025-10-29",
      "start_price": 226.993042,
      "end_price": 216.369995,
      "total_return": -0.046798997809658016,
      "cagr": -0.03155415775625792,
      "total_return_pct": -4.6799,
      "cagr_pct": -3.1554
    },
    {
      "ticker": "PG",
      "start_date": "2024-05-01",
      "end_date": "2025-10-29",
      "start_price": 157.317398,
      "end_price": 148.770004,
      "total_return": -0.054332158449218904,
      "cagr": -0.03668082815503815,
      "total_return_pct": -5.4332,
      "cagr_pct": -3.6681
    },
    {
      "ticker": "CRM",
      "start_date": "2024-05-01",
      "end_date": "2025-10-29",
      "start_price": 266.240387,
      "end_price": 251.460007,
      "total_return": -0.055515169646607965,
      "cagr": -0.037487149186719027,
      "total_return_pct": -5.5515,
      "cagr_pct": -3.7487
    },
    {
      "ticker": "7203.T",
      "start_date": "2024-05-01",
      "end_date": "2025-10-30",
      "start_price": 3436.442871,
      "end_price": 3178.0,
      "total_return": -0.07520650881982882,
      "cagr": -0.05086723557101713,
      "total_return_pct": -7.5207,
      "cagr_pct": -5.0867
    },
    {
      "ticker": "NESN.SW",
      "start_date": "2024-05-02",
      "end_date": "2025-10-29",
      "start_price": 88.636879,
      "end_price": 78.470001,
      "total_return": -0.11470256923570732,
      "cagr": -0.07840510970751913,
      "total_return_pct": -11.4703,
      "cagr_pct": -7.8405
    },
    {
      "ticker": "TTE.PA",
      "start_date": "2024-05-02",
      "end_date": "2025-10-29",
      "start_price": 61.347404,
      "end_price": 54.139999,
      "total_return": -0.1174850859857327,
      "cagr": -0.08034737128829317,
      "total_return_pct": -11.7485,
      "cagr_pct": -8.0347
    },
    {
      "ticker": "PEP",
      "start_date": "2024-05-01",
      "end_date": "2025-10-29",
      "start_price": 166.047485,
      "end_price": 146.160004,
      "total_return": -0.11976984563991766,
      "cagr": -0.08179993028451704,
      "total_return_pct": -11.977,
      "cagr_pct": -8.18
    },
    {
      "ticker": "DHR",
      "start_date": "2024-05-01",
      "end_date": "2025-10-29",
      "start_price": 244.899368,
      "end_price": 214.009995,
      "total_return": -0.12613088386249605,
      "cagr": -0.08624406801526607,
      "total_return_pct": -12.6131,
      "cagr_pct": -8.6244
    },
    {
      "ticker": "ACN",
      "start_date": "2024-05-01",
      "end_date": "2025-10-29",
      "start_price": 291.981812,
      "end_price": 247.75,
      "total_return": -0.15148824268420913,
      "cagr": -0.10406759014292655,
      "total_return_pct": -15.1488,
      "cagr_pct": -10.4068
    },
    {
      "ticker": "MC.PA",
      "start_date": "2024-05-02",
      "end_date": "2025-10-29",
      "start_price": 748.48877,
      "end_price": 618.799988,
      "total_return": -0.17326750516176803,
      "cagr": -0.11972292245450156,
      "total_return_pct": -17.3268,
      "cagr_pct": -11.9723
    },
    {
      "ticker": "CMCSA",
      "start_date": "2024-05-01",
      "end_date": "2025-10-29",
      "start_price": 36.238903,
      "end_price": 28.530001,
      "total_return": -0.21272449525574777,
      "cagr": -0.14785528613259658,
      "total_return_pct": -21.2724,
      "cagr_pct": -14.7855
    },
    {
      "ticker": "UNH",
      "start_date": "2024-05-01",
      "end_date": "2025-10-29",
      "start_price": 470.164948,
      "end_price": 355.26001,
      "total_return": -0.24439282075947177,
      "cagr": -0.17094102674222145,
      "total_return_pct": -24.4393,
      "cagr_pct": -17.0941
    },
    {
      "ticker": "COP",
      "start_date": "2024-05-01",
      "end_date": "2025-10-29",
      "start_price": 118.834824,
      "end_price": 88.080002,
      "total_return": -0.2588031087477476,
      "cagr": -0.18155162958732984,
      "total_return_pct": -25.8803,
      "cagr_pct": -18.1552
    },
    {
      "ticker": "ADBE",
      "start_date": "2024-05-01",
      "end_date": "2025-10-29",
      "start_price": 469.390015,
      "end_price": 337.859985,
      "total_return": -0.2802148004690471,
      "cagr": -0.19744459283321414,
      "total_return_pct": -28.0215,
      "cagr_pct": -19.7445
    },
    {
      "ticker": "MRK",
      "start_date": "2024-05-01",
      "end_date": "2025-10-29",
      "start_price": 122.640961,
      "end_price": 86.580002,
      "total_return": -0.2940368263460389,
      "cagr": -0.20778723444453762,
      "total_return_pct": -29.4037,
      "cagr_pct": -20.7787
    },
    {
      "ticker": "ELV",
      "start_date": "2024-05-01",
      "end_date": "2025-10-29",
      "start_price": 512.322388,
      "end_price": 336.359985,
      "total_return": -0.34346030267253924,
      "cagr": -0.24533252113352244,
      "total_return_pct": -34.346,
      "cagr_pct": -24.5333
    },
    {
      "ticker": "NVO",
      "start_date": "2024-05-01",
      "end_date": "2025-10-29",
      "start_price": 126.686729,
      "end_price": 51.369999,
      "total_return": -0.594511602260585,
      "cagr": -0.4532927881658628,
      "total_return_pct": -59.4512,
      "cagr_pct": -45.3293
    }
  ]
}