[
  {
    "ticker": "VT",
    "start_date": "2024-05-01",
    "end_date": "2025-10-29",
    "start_price": 103.444954,
    "end_price": 141.589996,
    "total_return": 0.3687472513110919,
    "cagr": 0.23365654944177017,
    "total_return_pct": 36.87472513110919,
    "cagr_pct": 23.365654944177017,
    "twd_return_pct": 28.894946966291446,
    "company_name": "Vanguard Total World Stock ETF"
  },
  {
    "ticker": "MSFT",
    "start_date": "2024-05-01",
    "end_date": "2025-10-29",
    "start_price": 390.58728,
    "end_price": 541.549988,
    "total_return": 0.38650185283516447,
    "cagr": 0.2443385205980697,
    "total_return_pct": 38.65018528351645,
    "cagr_pct": 24.43385205980697,
    "twd_return_pct": 30.566898029324374,
    "company_name": "Microsoft Corp"
  },
  {
    "ticker": "AAPL",
    "start_date": "2024-05-01",
    "end_date": "2025-10-29",
    "start_price": 168.092896,
    "end_price": 269.700012,
    "total_return": 0.6044700246983152,
    "cagr": 0.3720117164428727,
    "total_return_pct": 60.447002469831524,
    "cagr_pct": 37.20117164428727,
    "twd_return_pct": 51.09296368953211,
    "company_name": "Apple Inc"
  },
  {
    "ticker": "NVDA",
    "start_date": "2024-05-01",
    "end_date": "2025-10-29",
    "start_price": 83.003265,
    "end_price": 207.039993,
    "total_return": 1.4943596174937523,
    "cagr": 0.8430968929259186,
    "total_return_pct": 149.43596174937522,
    "cagr_pct": 84.30968929259186,
    "twd_return_pct": 134.89387854751763,
    "company_name": "NVIDIA Corp"
  },
  {
    "ticker": "AMZN",
    "start_date": "2024-05-01",
    "end_date": "2025-10-29",
    "start_price": 179.0,
    "end_price": 230.300003,
    "total_return": 0.28659219581987605,
    "cagr": 0.18361690688670396,
    "total_return_pct": 28.659219581987607,
    "cagr_pct": 18.361690688670397,
    "twd_return_pct": 21.158404291659828,
    "company_name": "Amazon.com Inc"
  },
  {
    "ticker": "GOOGL",
    "start_date": "2024-05-01",
    "end_date": "2025-10-29",
    "start_price": 162.737579,
    "end_price": 274.570007,
    "total_return": 0.6871948595287276,
    "cagr": 0.4189384676024923,
    "total_return_pct": 68.71948595287276,
    "cagr_pct": 41.89384676024923,
    "twd_return_pct": 58.88316249215806,
    "company_name": "Alphabet Inc"
  },
  {
    "ticker": "META",
    "start_date": "2024-05-01",
    "end_date": "2025-10-29",
    "start_price": 436.96225,
    "end_price": 751.669983,
    "total_return": 0.7202172117388428,
    "cagr": 0.43745700907319374,
    "total_return_pct": 72.02172117388427,
    "cagr_pct": 43.745700907319375,
    "twd_return_pct": 61.99287784153893,
    "company_name": "Meta Platforms Inc"
  },
  {
    "ticker": "GOOG",
    "start_date": "2024-05-01",
    "end_date": "2025-10-29",
    "start_price": 164.444672,
    "end_price": 275.170013,
    "total_return": 0.6733288509671389,
    "cagr": 0.41112686923940234,
    "total_return_pct": 67.3328850967139,
    "cagr_pct": 41.11268692394023,
    "twd_return_pct": 57.57740028042162,
    "company_name": "Alphabet Inc"
  },
  {
    "ticker": "LLY",
    "start_date": "2024-05-01",
    "end_date": "2025-10-29",
    "start_price": 768.46936,
    "end_price": 813.530029,
    "total_return": 0.058636910292295896,
    "cagr": 0.03885438340345648,
    "total_return_pct": 5.86369102922959,
    "cagr_pct": 3.8854383403456483,
    "twd_return_pct": -0.3081479959291644,
    "company_name": "Eli Lilly & Co"
  },
  {
    "ticker": "BRK-B",
    "start_date": "2024-05-01",
    "end_date": "2025-10-29",
    "start_price": 398.579987,
    "end_price": 475.76001,
    "total_return": 0.1936374775289076,
    "cagr": 0.12570420275524885,
    "total_return_pct": 19.36374775289076,
    "cagr_pct": 12.570420275524885,
    "twd_return_pct": 12.404857226703726,
    "company_name": "Berkshire Hathaway Inc"
  },
  {
    "ticker": "2330.TW",
    "start_date": "2024-05-02",
    "end_date": "2025-10-30",
    "start_price": 752.925476,
    "end_price": 1505.0,
    "total_return": 0.9988698056109426,
    "cagr": 0.5893209725913768,
    "total_return_pct": 99.88698056109426,
    "cagr_pct": 58.932097259137684,
    "twd_return_pct": 88.23359633413124,
    "company_name": "Taiwan Semiconductor Manufacturing Co Ltd"
  },
  {
    "ticker": "AVGO",
    "start_date": "2024-05-01",
    "end_date": "2025-10-29",
    "start_price": 122.287102,
    "end_price": 385.980011,
    "total_return": 2.1563427824897223,
    "cagr": 1.1574078876113352,
    "total_return_pct": 215.63427824897224,
    "cagr_pct": 115.74078876113352,
    "twd_return_pct": 197.23284205082422,
    "company_name": "Broadcom Inc"
  },
  {
    "ticker": "JPM",
    "start_date": "2024-05-01",
    "end_date": "2025-10-29",
    "start_price": 185.709351,
    "end_price": 305.51001,
    "total_return": 0.6450976151803913,
    "cagr": 0.39515585545775744,
    "total_return_pct": 64.50976151803913,
    "cagr_pct": 39.51558554577574,
    "twd_return_pct": 54.91886442872212,
    "company_name": "JPMorgan Chase & Co"
  },
  {
    "ticker": "TSLA",
    "start_date": "2024-05-01",
    "end_date": "2025-10-29",
    "start_price": 179.990005,
    "end_price": 461.51001,
    "total_return": 1.5640868697187353,
    "cagr": 0.8774052347485926,
    "total_return_pct": 156.40868697187352,
    "cagr_pct": 87.74052347485926,
    "twd_return_pct": 141.460094822316,
    "company_name": "Tesla Inc"
  },
  {
    "ticker": "XOM",
    "start_date": "2024-05-01",
    "end_date": "2025-10-29",
    "start_price": 110.191711,
    "end_price": 116.449997,
    "total_return": 0.05679452148881592,
    "cagr": 0.03764458865282316,
    "total_return_pct": 5.679452148881592,
    "cagr_pct": 3.7644588652823163,
    "twd_return_pct": -0.481645774199313,
    "company_name": "Exxon Mobil Corp"
  },
  {
    "ticker": "UNH",
    "start_date": "2024-05-01",
    "end_date": "2025-10-29",
    "start_price": 470.164948,
    "end_price": 355.26001,
    "total_return": -0.24439282075947177,
    "cagr": -0.17094102674222145,
    "total_return_pct": -24.439282075947176,
    "cagr_pct": -17.094102674222146,
    "twd_return_pct": -28.844461822834333,
    "company_name": "UnitedHealth Group Inc"
  },
  {
    "ticker": "V",
    "start_date": "2024-05-01",
    "end_date": "2025-10-29",
    "start_price": 264.43515,
    "end_price": 341.279999,
    "total_return": 0.29059997731105014,
    "cagr": 0.1860820843601445,
    "total_return_pct": 29.059997731105014,
    "cagr_pct": 18.60820843601445,
    "twd_return_pct": 21.53581712829753,
    "company_name": "Visa Inc"
  },
  {
    "ticker": "NVO",
    "start_date": "2024-05-01",
    "end_date": "2025-10-29",
    "start_price": 126.686729,
    "end_price": 51.369999,
    "total_return": -0.594511602260585,
    "cagr": -0.4532927881658628,
    "total_return_pct": -59.4511602260585,
    "cagr_pct": -45.32927881658628,
    "twd_return_pct": -61.815152160485034,
    "company_name": "Novo Nordisk A/S"
  },
  {
    "ticker": "PG",
    "start_date": "2024-05-01",
    "end_date": "2025-10-29",
    "start_price": 157.317398,
    "end_price": 148.770004,
    "total_return": -0.054332158449218904,
    "cagr": -0.03668082815503815,
    "total_return_pct": -5.43321584492189,
    "cagr_pct": -3.6680828155038148,
    "twd_return_pct": -10.94644671055387,
    "company_name": "Procter & Gamble Co/The"
  },
  {
    "ticker": "MA",
    "start_date": "2024-05-01",
    "end_date": "2025-10-29",
    "start_price": 438.311707,
    "end_price": 554.580017,
    "total_return": 0.2652639863623558,
    "cagr": 0.170454931222207,
    "total_return_pct": 26.526398636235584,
    "cagr_pct": 17.0454931222207,
    "twd_return_pct": 19.149926521728446,
    "company_name": "Mastercard Inc"
  },
  {
    "ticker": "JNJ",
    "start_date": "2024-05-01",
    "end_date": "2025-10-29",
    "start_price": 144.177399,
    "end_price": 186.600006,
    "total_return": 0.2942389570750179,
    "cagr": 0.18831821840252805,
    "total_return_pct": 29.423895707501792,
    "cagr_pct": 18.831821840252804,
    "twd_return_pct": 21.87849990135058,
    "company_name": "Johnson & Johnson"
  },
  {
    "ticker": "ASML",
    "start_date": "2024-05-01",
    "end_date": "2025-10-29",
    "start_price": 841.258301,
    "end_price": 1070.839966,
    "total_return": 0.2729027039921714,
    "cagr": 0.17517728522660736,
    "total_return_pct": 27.290270399217142,
    "cagr_pct": 17.517728522660736,
    "twd_return_pct": 19.869264663114606,
    "company_name": "ASML Holding NV"
  },
  {
    "ticker": "HD",
    "start_date": "2024-05-01",
    "end_date": "2025-10-29",
    "start_price": 320.099121,
    "end_price": 378.040009,
    "total_return": 0.18100920506495943,
    "cagr": 0.11772321198009594,
    "total_return_pct": 18.100920506495942,
    "cagr_pct": 11.772321198009594,
    "twd_return_pct": 11.215652639839856,
    "company_name": "Home Depot Inc/The"
  },
  {
    "ticker": "MRK",
    "start_date": "2024-05-01",
    "end_date": "2025-10-29",
    "start_price": 122.640961,
    "end_price": 86.580002,
    "total_return": -0.2940368263460389,
    "cagr": -0.20778723444453762,
    "total_return_pct": -29.40368263460389,
    "cagr_pct": -20.77872344445376,
    "twd_return_pct": -33.51943849303076,
    "company_name": "Merck & Co Inc"
  },
  {
    "ticker": "COST",
    "start_date": "2024-05-01",
    "end_date": "2025-10-29",
    "start_price": 717.511047,
    "end_price": 912.419983,
    "total_return": 0.2716459018479629,
    "cagr": 0.174400960041319,
    "total_return_pct": 27.16459018479629,
    "cagr_pct": 17.4400960041319,
    "twd_return_pct": 19.750911588381715,
    "company_name": "Costco Wholesale Corp"
  },
  {
    "ticker": "ABBV",
    "start_date": "2024-05-01",
    "end_date": "2025-10-29",
    "start_price": 153.607407,
    "end_price": 225.139999,
    "total_return": 0.46568452882068456,
    "cagr": 0.2914387055442995,
    "total_return_pct": 46.568452882068456,
    "cagr_pct": 29.143870554429952,
    "twd_return_pct": 38.02353168614183,
    "company_name": "AbbVie Inc"
  },
  {
    "ticker": "CVX",
    "start_date": "2024-05-01",
    "end_date": "2025-10-29",
    "start_price": 149.504196,
    "end_price": 155.100006,
    "total_return": 0.03742911623880496,
    "cagr": 0.024885833103254207,
    "total_return_pct": 3.742911623880496,
    "cagr_pct": 2.4885833103254207,
    "twd_return_pct": -2.3052862456522716,
    "company_name": "Chevron Corp"
  },
  {
    "ticker": "7203.T",
    "start_date": "2024-05-01",
    "end_date": "2025-10-30",
    "start_price": 3436.442871,
    "end_price": 3178.0,
    "total_return": -0.07520650881982882,
    "cagr": -0.05086723557101713,
    "total_return_pct": -7.520650881982882,
    "cagr_pct": -5.086723557101713,
    "twd_return_pct": -12.912184564199446,
    "company_name": "Toyota Motor Corp"
  },
  {
    "ticker": "0700.HK",
    "start_date": "2024-05-02",
    "end_date": "2025-10-30",
    "start_price": 354.221313,
    "end_price": 650.0,
    "total_return": 0.835010981187071,
    "cagr": 0.5009377479509596,
    "total_return_pct": 83.50109811870709,
    "cagr_pct": 50.09377479509596,
    "twd_return_pct": 72.80300864612465,
    "company_name": "Tencent Holdings Ltd"
  },
  {
    "ticker": "NESN.SW",
    "start_date": "2024-05-02",
    "end_date": "2025-10-29",
    "start_price": 88.636879,
    "end_price": 78.470001,
    "total_return": -0.11470256923570732,
    "cagr": -0.07840510970751913,
    "total_return_pct": -11.470256923570732,
    "cagr_pct": -7.840510970751913,
    "twd_return_pct": -16.631529101918662,
    "company_name": "Nestle SA"
  },
  {
    "ticker": "005930.KS",
    "start_date": "2024-05-02",
    "end_date": "2025-10-30",
    "start_price": 75779.609375,
    "end_price": 104400.0,
    "total_return": 0.3776793105830125,
    "cagr": 0.23903617669189914,
    "total_return_pct": 37.76793105830125,
    "cagr_pct": 23.903617669189913,
    "twd_return_pct": 29.736079107416245,
    "company_name": "Samsung Electronics Co Ltd"
  },
  {
    "ticker": "BAC",
    "start_date": "2024-05-01",
    "end_date": "2025-10-29",
    "start_price": 35.649784,
    "end_price": 52.580002,
    "total_return": 0.47490379467837407,
    "cagr": 0.2968671584555862,
    "total_return_pct": 47.49037946783741,
    "cagr_pct": 29.68671584555862,
    "twd_return_pct": 38.891710075290554,
    "company_name": "Bank of America Corp"
  },
  {
    "ticker": "WMT",
    "start_date": "2024-05-01",
    "end_date": "2025-10-29",
    "start_price": 57.9156,
    "end_price": 102.459999,
    "total_return": 0.7691260972451539,
    "cagr": 0.4646698419092268,
    "total_return_pct": 76.91260972451539,
    "cagr_pct": 46.46698419092268,
    "twd_return_pct": 66.59862824394362,
    "company_name": "Walmart Inc"
  },
  {
    "ticker": "AMD",
    "start_date": "2024-05-01",
    "end_date": "2025-10-29",
    "start_price": 144.270004,
    "end_price": 264.329987,
    "total_return": 0.8321894970839923,
    "cagr": 0.4993935257454618,
    "total_return_pct": 83.21894970839922,
    "cagr_pct": 49.93935257454618,
    "twd_return_pct": 72.53730945039352,
    "company_name": "Advanced Micro Devices Inc"
  },
  {
    "ticker": "CRM",
    "start_date": "2024-05-01",
    "end_date": "2025-10-29",
    "start_price": 266.240387,
    "end_price": 251.460007,
    "total_return": -0.055515169646607965,
    "cagr": -0.037487149186719027,
    "total_return_pct": -5.551516964660797,
    "cagr_pct": -3.7487149186719027,
    "twd_return_pct": -11.057850890837651,
    "company_name": "Salesforce Inc"
  },
  {
    "ticker": "PEP",
    "start_date": "2024-05-01",
    "end_date": "2025-10-29",
    "start_price": 166.047485,
    "end_price": 146.160004,
    "total_return": -0.11976984563991766,
    "cagr": -0.08179993028451704,
    "total_return_pct": -11.976984563991767,
    "cagr_pct": -8.179993028451705,
    "twd_return_pct": -17.10871458869031,
    "company_name": "PepsiCo Inc"
  },
  {
    "ticker": "KO",
    "start_date": "2024-05-01",
    "end_date": "2025-10-29",
    "start_price": 59.252613,
    "end_price": 68.349998,
    "total_return": 0.1535355984403759,
    "cagr": 0.10026174535448207,
    "total_return_pct": 15.35355984403759,
    "cagr_pct": 10.026174535448206,
    "twd_return_pct": 8.628462736476461,
    "company_name": "Coca-Cola Co/The"
  },
  {
    "ticker": "NFLX",
    "start_date": "2024-05-01",
    "end_date": "2025-10-29",
    "start_price": 551.710022,
    "end_price": 1100.410034,
    "total_return": 0.9945442177126624,
    "cagr": 0.5870193955714411,
    "total_return_pct": 99.45442177126624,
    "cagr_pct": 58.701939557144115,
    "twd_return_pct": 87.82625566388494,
    "company_name": "Netflix Inc"
  },
  {
    "ticker": "SHEL.L",
    "start_date": "2024-05-01",
    "end_date": "2025-10-29",
    "start_price": 2817.304199,
    "end_price": 2875.5,
    "total_return": 0.020656555581533453,
    "cagr": 0.013771509135073856,
    "total_return_pct": 2.0656555581533453,
    "cagr_pct": 1.3771509135073856,
    "twd_return_pct": -3.8847585071213553,
    "company_name": "Shell PLC"
  },
  {
    "ticker": "AZN.L",
    "start_date": "2024-05-01",
    "end_date": "2025-10-29",
    "start_price": 12166.665039,
    "end_price": 12560.0,
    "total_return": 0.03232890522379406,
    "cagr": 0.02151251874087934,
    "total_return_pct": 3.2328905223794058,
    "cagr_pct": 2.151251874087934,
    "twd_return_pct": -2.785573185163581,
    "company_name": "AstraZeneca PLC"
  },
  {
    "ticker": "TMO",
    "start_date": "2024-05-01",
    "end_date": "2025-10-29",
    "start_price": 572.214844,
    "end_price": 558.309998,
    "total_return": -0.024300044543201782,
    "cagr": -0.016321760125206697,
    "total_return_pct": -2.430004454320178,
    "cagr_pct": -1.6321760125206697,
    "twd_return_pct": -8.118322142271616,
    "company_name": "Thermo Fisher Scientific Inc"
  },
  {
    "ticker": "WFC",
    "start_date": "2024-05-01",
    "end_date": "2025-10-29",
    "start_price": 57.453186,
    "end_price": 86.0,
    "total_return": 0.4968708601708465,
    "cagr": 0.3097566707109485,
    "total_return_pct": 49.687086017084646,
    "cagr_pct": 30.975667071094847,
    "twd_return_pct": 40.96034892657965,
    "company_name": "Wells Fargo & Co"
  },
  {
    "ticker": "LIN",
    "start_date": "2024-05-01",
    "end_date": "2025-10-29",
    "start_price": 434.346313,
    "end_price": 432.01001,
    "total_return": -0.005378896144501488,
    "cagr": -0.003601456364653144,
    "total_return_pct": -0.5378896144501488,
    "cagr_pct": -0.3601456364653144,
    "twd_return_pct": -6.336517344449599,
    "company_name": "Linde PLC"
  },
  {
    "ticker": "ADBE",
    "start_date": "2024-05-01",
    "end_date": "2025-10-29",
    "start_price": 469.390015,
    "end_price": 337.859985,
    "total_return": -0.2802148004690471,
    "cagr": -0.19744459283321414,
    "total_return_pct": -28.021480046904713,
    "cagr_pct": -19.744459283321415,
    "twd_return_pct": -32.21781813129121,
    "company_name": "Adobe Inc"
  },
  {
    "ticker": "MC.PA",
    "start_date": "2024-05-02",
    "end_date": "2025-10-29",
    "start_price": 748.48877,
    "end_price": 618.799988,
    "total_return": -0.17326750516176803,
    "cagr": -0.11972292245450156,
    "total_return_pct": -17.3267505161768,
    "cagr_pct": -11.972292245450156,
    "twd_return_pct": -22.14658990152436,
    "company_name": "LVMH Moet Hennessy Louis Vuitton SE"
  },
  {
    "ticker": "DIS",
    "start_date": "2024-05-01",
    "end_date": "2025-10-29",
    "start_price": 109.022591,
    "end_price": 110.239998,
    "total_return": 0.01116655932909949,
    "cagr": 0.00745619854841717,
    "total_return_pct": 1.116655932909949,
    "cagr_pct": 0.745619854841717,
    "twd_return_pct": -4.778431581164854,
    "company_name": "Walt Disney Co/The"
  },
  {
    "ticker": "NOVN.SW",
    "start_date": "2024-05-02",
    "end_date": "2025-10-29",
    "start_price": 85.801888,
    "end_price": 98.5,
    "total_return": 0.1479933933386537,
    "cagr": 0.09690846622906868,
    "total_return_pct": 14.799339333865369,
    "cagr_pct": 9.690846622906868,
    "twd_return_pct": 8.106553207906785,
    "company_name": "Novartis AG"
  },
  {
    "ticker": "MCD",
    "start_date": "2024-05-01",
    "end_date": "2025-10-29",
    "start_price": 264.899658,
    "end_price": 302.350006,
    "total_return": 0.1413755991775334,
    "cagr": 0.09248931532843163,
    "total_return_pct": 14.13755991775334,
    "cagr_pct": 9.248931532843162,
    "twd_return_pct": 7.483355443225004,
    "company_name": "McDonald's Corp"
  },
  {
    "ticker": "SAP.DE",
    "start_date": "2024-05-02",
    "end_date": "2025-10-29",
    "start_price": 164.943604,
    "end_price": 224.300003,
    "total_return": 0.35985875336178164,
    "cagr": 0.22875512162595646,
    "total_return_pct": 35.98587533617816,
    "cagr_pct": 22.875512162595648,
    "twd_return_pct": 28.05791699549962,
    "company_name": "SAP SE"
  },
  {
    "ticker": "ACN",
    "start_date": "2024-05-01",
    "end_date": "2025-10-29",
    "start_price": 291.981812,
    "end_price": 247.75,
    "total_return": -0.15148824268420913,
    "cagr": -0.10406759014292655,
    "total_return_pct": -15.148824268420913,
    "cagr_pct": -10.406759014292655,
    "twd_return_pct": -20.095636462661993,
    "company_name": "Accenture PLC"
  },
  {
    "ticker": "CSCO",
    "start_date": "2024-05-01",
    "end_date": "2025-10-29",
    "start_price": 44.931202,
    "end_price": 71.330002,
    "total_return": 0.5875382531395272,
    "cagr": 0.3623091260663005,
    "total_return_pct": 58.753825313952724,
    "cagr_pct": 36.23091260663005,
    "twd_return_pct": 49.49849853533739,
    "company_name": "Cisco Systems Inc"
  },
  {
    "ticker": "QCOM",
    "start_date": "2024-05-01",
    "end_date": "2025-10-29",
    "start_price": 159.020615,
    "end_price": 178.669998,
    "total_return": 0.12356500816815119,
    "cagr": 0.08105546160090249,
    "total_return_pct": 12.35650081681512,
    "cagr_pct": 8.105546160090249,
    "twd_return_pct": 5.806131849611473,
    "company_name": "QUALCOMM Inc"
  },
  {
    "ticker": "ABT",
    "start_date": "2024-05-01",
    "end_date": "2025-10-29",
    "start_price": 103.276215,
    "end_price": 124.43,
    "total_return": 0.20482727593742012,
    "cagr": 0.13275275727212477,
    "total_return_pct": 20.482727593742013,
    "cagr_pct": 13.275275727212478,
    "twd_return_pct": 13.458600692524136,
    "company_name": "Abbott Laboratories"
  },
  {
    "ticker": "GE",
    "start_date": "2024-05-01",
    "end_date": "2025-10-29",
    "start_price": 158.215607,
    "end_price": 314.279999,
    "total_return": 0.9864032718097666,
    "cagr": 0.5826832399822115,
    "total_return_pct": 98.64032718097666,
    "cagr_pct": 58.26832399822115,
    "twd_return_pct": 87.05962267930427,
    "company_name": "General Electric Co"
  },
  {
    "ticker": "ORCL",
    "start_date": "2024-05-01",
    "end_date": "2025-10-29",
    "start_price": 112.927597,
    "end_price": 275.299988,
    "total_return": 1.437845088309773,
    "cagr": 0.8150561846708568,
    "total_return_pct": 143.7845088309773,
    "cagr_pct": 81.50561846708568,
    "twd_return_pct": 129.57190457824294,
    "company_name": "Oracle Corp"
  },
  {
    "ticker": "INTU",
    "start_date": "2024-05-01",
    "end_date": "2025-10-29",
    "start_price": 609.294983,
    "end_price": 656.039978,
    "total_return": 0.0767198096625068,
    "cagr": 0.05069169006540464,
    "total_return_pct": 7.67198096625068,
    "cagr_pct": 5.069169006540464,
    "twd_return_pct": 1.394718879666379,
    "company_name": "Intuit Inc"
  },
  {
    "ticker": "CAT",
    "start_date": "2024-05-01",
    "end_date": "2025-10-29",
    "start_price": 323.659149,
    "end_price": 585.48999,
    "total_return": 0.8089709243071366,
    "cagr": 0.4866557525444215,
    "total_return_pct": 80.89709243071366,
    "cagr_pct": 48.66557525444215,
    "twd_return_pct": 70.35081614139209,
    "company_name": "Caterpillar Inc"
  },
  {
    "ticker": "AMAT",
    "start_date": "2024-05-01",
    "end_date": "2025-10-29",
    "start_price": 191.276398,
    "end_price": 235.75,
    "total_return": 0.2325096186906137,
    "cagr": 0.1500976908110181,
    "total_return_pct": 23.25096186906137,
    "cagr_pct": 15.009769081101808,
    "twd_return_pct": 16.065447279911083,
    "company_name": "Applied Materials Inc"
  },
  {
    "ticker": "VZ",
    "start_date": "2024-05-01",
    "end_date": "2025-10-29",
    "start_price": 35.529789,
    "end_price": 40.209999,
    "total_return": 0.1317263695923554,
    "cagr": 0.08630219703417508,
    "total_return_pct": 13.17263695923554,
    "cagr_pct": 8.630219703417508,
    "twd_return_pct": 6.574687364106846,
    "company_name": "Verizon Communications Inc"
  },
  {
    "ticker": "HSBA.L",
    "start_date": "2024-05-01",
    "end_date": "2025-10-29",
    "start_price": 696.788025,
    "end_price": 1073.400024,
    "total_return": 0.54049723309252,
    "cagr": 0.3351710538804813,
    "total_return_pct": 54.049723309251995,
    "cagr_pct": 33.51710538804813,
    "twd_return_pct": 45.068645048222564,
    "company_name": "HSBC Holdings PLC"
  },
  {
    "ticker": "DHR",
    "start_date": "2024-05-01",
    "end_date": "2025-10-29",
    "start_price": 244.899368,
    "end_price": 214.009995,
    "total_return": -0.12613088386249605,
    "cagr": -0.08624406801526607,
    "total_return_pct": -12.613088386249604,
    "cagr_pct": -8.624406801526607,
    "twd_return_pct": -17.707733643204882,
    "company_name": "Danaher Corp"
  },
  {
    "ticker": "TXN",
    "start_date": "2024-05-01",
    "end_date": "2025-10-29",
    "start_price": 167.776154,
    "end_price": 160.259995,
    "total_return": -0.044798732703868804,
    "cagr": -0.03019513961421283,
    "total_return_pct": -4.47987327038688,
    "cagr_pct": -3.019513961421283,
    "twd_return_pct": -10.048683880581477,
    "company_name": "Texas Instruments Inc"
  },
  {
    "ticker": "9988.HK",
    "start_date": "2024-05-02",
    "end_date": "2025-10-30",
    "start_price": 75.733734,
    "end_price": 170.800003,
    "total_return": 1.2552697950511011,
    "cagr": 0.7229563443006124,
    "total_return_pct": 125.52697950511012,
    "cagr_pct": 72.29563443006124,
    "twd_return_pct": 112.37878676968487,
    "company_name": "Alibaba Group Holding Ltd"
  },
  {
    "ticker": "IBM",
    "start_date": "2024-05-01",
    "end_date": "2025-10-29",
    "start_price": 156.967331,
    "end_price": 308.209991,
    "total_return": 0.9635295422547909,
    "cagr": 0.5704682707657125,
    "total_return_pct": 96.3529542254791,
    "cagr_pct": 57.04682707657125,
    "twd_return_pct": 84.9056032611204,
    "company_name": "International Business Machines Corp"
  },
  {
    "ticker": "COP",
    "start_date": "2024-05-01",
    "end_date": "2025-10-29",
    "start_price": 118.834824,
    "end_price": 88.080002,
    "total_return": -0.2588031087477476,
    "cagr": -0.18155162958732984,
    "total_return_pct": -25.880310874774757,
    "cagr_pct": -18.155162958732983,
    "twd_return_pct": -30.201478835462947,
    "company_name": "ConocoPhillips"
  },
  {
    "ticker": "CMCSA",
    "start_date": "2024-05-01",
    "end_date": "2025-10-29",
    "start_price": 36.238903,
    "end_price": 28.530001,
    "total_return": -0.21272449525574777,
    "cagr": -0.14785528613259658,
    "total_return_pct": -21.27244952557478,
    "cagr_pct": -14.785528613259658,
    "twd_return_pct": -25.86225518650771,
    "company_name": "Comcast Corp"
  },
  {
    "ticker": "TTE.PA",
    "start_date": "2024-05-02",
    "end_date": "2025-10-29",
    "start_price": 61.347404,
    "end_price": 54.139999,
    "total_return": -0.1174850859857327,
    "cagr": -0.08034737128829317,
    "total_return_pct": -11.74850859857327,
    "cagr_pct": -8.034737128829317,
    "twd_return_pct": -16.89355874149149,
    "company_name": "TotalEnergies SE"
  },
  {
    "ticker": "PM",
    "start_date": "2024-05-01",
    "end_date": "2025-10-29",
    "start_price": 90.386787,
    "end_price": 146.770004,
    "total_return": 0.6237993236701029,
    "cagr": 0.383046850812663,
    "total_return_pct": 62.37993236701029,
    "cagr_pct": 38.3046850812663,
    "twd_return_pct": 52.91320403228177,
    "company_name": "Philip Morris International Inc"
  },
  {
    "ticker": "AMGN",
    "start_date": "2024-05-01",
    "end_date": "2025-10-29",
    "start_price": 264.660065,
    "end_price": 291.769989,
    "total_return": 0.10243299965718755,
    "cagr": 0.06741121943781003,
    "total_return_pct": 10.243299965718755,
    "cagr_pct": 6.741121943781003,
    "twd_return_pct": 3.8161303254419687,
    "company_name": "Amgen Inc"
  },
  {
    "ticker": "RTX",
    "start_date": "2024-05-01",
    "end_date": "2025-10-29",
    "start_price": 98.113197,
    "end_price": 176.360001,
    "total_return": 0.7975155780845145,
    "cagr": 0.4803513942142621,
    "total_return_pct": 79.75155780845145,
    "cagr_pct": 48.03513942142621,
    "twd_return_pct": 69.27206603436463,
    "company_name": "RTX Corp"
  },
  {
    "ticker": "PFE",
    "start_date": "2024-05-01",
    "end_date": "2025-10-29",
    "start_price": 24.672352,
    "end_price": 24.290001,
    "total_return": -0.015497141259756764,
    "cagr": -0.010393683154164224,
    "total_return_pct": -1.5497141259756764,
    "cagr_pct": -1.0393683154164224,
    "twd_return_pct": -7.289352622309342,
    "company_name": "Pfizer Inc"
  },
  {
    "ticker": "UNP",
    "start_date": "2024-05-01",
    "end_date": "2025-10-29",
    "start_price": 226.993042,
    "end_price": 216.369995,
    "total_return": -0.046798997809658016,
    "cagr": -0.03155415775625792,
    "total_return_pct": -4.679899780965801,
    "cagr_pct": -3.1554157756257917,
    "twd_return_pct": -10.237048872352062,
    "company_name": "Union Pacific Corp"
  },
  {
    "ticker": "ROG.SW",
    "start_date": "2024-05-02",
    "end_date": "2025-10-29",
    "start_price": 207.245987,
    "end_price": 260.399994,
    "total_return": 0.25647785871862117,
    "cagr": 0.16533807495818986,
    "total_return_pct": 25.647785871862116,
    "cagr_pct": 16.533807495818987,
    "twd_return_pct": 18.3225367639821,
    "company_name": "Roche Holding AG"
  },
  {
    "ticker": "NOW",
    "start_date": "2024-05-01",
    "end_date": "2025-10-29",
    "start_price": 685.609985,
    "end_price": 911.700012,
    "total_return": 0.3297647812692457,
    "cagr": 0.21004053317205873,
    "total_return_pct": 32.97647812692457,
    "cagr_pct": 21.004053317205873,
    "twd_return_pct": 25.223967240965383,
    "company_name": "ServiceNow Inc"
  },
  {
    "ticker": "SIE.DE",
    "start_date": "2024-05-02",
    "end_date": "2025-10-29",
    "start_price": 171.194534,
    "end_price": 245.75,
    "total_return": 0.43550143701916455,
    "cagr": 0.274152002657857,
    "total_return_pct": 43.550143701916454,
    "cagr_pct": 27.4152002657857,
    "twd_return_pct": 35.18118952742037,
    "company_name": "Siemens AG"
  },
  {
    "ticker": "BHP.AX",
    "start_date": "2024-05-01",
    "end_date": "2025-10-30",
    "start_price": 39.427185,
    "end_price": 43.880001,
    "total_return": 0.1129377104377105,
    "cagr": 0.07406392421804919,
    "total_return_pct": 11.29377104377105,
    "cagr_pct": 7.406392421804919,
    "twd_return_pct": 4.805359080169902,
    "company_name": "BHP Group Ltd"
  },
  {
    "ticker": "NEE",
    "start_date": "2024-05-01",
    "end_date": "2025-10-29",
    "start_price": 65.685501,
    "end_price": 81.760002,
    "total_return": 0.24471916585458198,
    "cagr": 0.15770676768930714,
    "total_return_pct": 24.471916585458196,
    "cagr_pct": 15.770676768930713,
    "twd_return_pct": 17.215220499674388,
    "company_name": "NextEra Energy Inc"
  },
  {
    "ticker": "AXP",
    "start_date": "2024-05-01",
    "end_date": "2025-10-29",
    "start_price": 227.718109,
    "end_price": 358.220001,
    "total_return": 0.573085261369574,
    "cagr": 0.3539998457362372,
    "total_return_pct": 57.308526136957404,
    "cagr_pct": 35.39998457362372,
    "twd_return_pct": 48.137460107016935,
    "company_name": "American Express Co"
  },
  {
    "ticker": "RY.TO",
    "start_date": "2024-05-01",
    "end_date": "2025-10-29",
    "start_price": 127.297356,
    "end_price": 204.550003,
    "total_return": 0.606867652547159,
    "cagr": 0.3733829082357343,
    "total_return_pct": 60.6867652547159,
    "cagr_pct": 37.33829082357343,
    "twd_return_pct": 51.31874833613183,
    "company_name": "Royal Bank of Canada"
  },
  {
    "ticker": "GS",
    "start_date": "2024-05-01",
    "end_date": "2025-10-29",
    "start_price": 413.449615,
    "end_price": 783.059998,
    "total_return": 0.8939671685322548,
    "cagr": 0.5330276021977891,
    "total_return_pct": 89.39671685322548,
    "cagr_pct": 53.30276021977891,
    "twd_return_pct": 78.35491359710312,
    "company_name": "Goldman Sachs Group Inc/The"
  },
  {
    "ticker": "SPGI",
    "start_date": "2024-05-01",
    "end_date": "2025-10-29",
    "start_price": 411.6138,
    "end_price": 473.049988,
    "total_return": 0.14925687072895188,
    "cagr": 0.09752997466944002,
    "total_return_pct": 14.925687072895188,
    "cagr_pct": 9.752997466944002,
    "twd_return_pct": 8.225534890653252,
    "company_name": "S&P Global Inc"
  },
  {
    "ticker": "LOW",
    "start_date": "2024-05-01",
    "end_date": "2025-10-29",
    "start_price": 221.038162,
    "end_price": 238.490005,
    "total_return": 0.07895398281245769,
    "cagr": 0.05214962437110415,
    "total_return_pct": 7.895398281245769,
    "cagr_pct": 5.214962437110415,
    "twd_return_pct": 1.6051109950847575,
    "company_name": "Lowe's Cos Inc"
  },
  {
    "ticker": "UBER",
    "start_date": "2024-05-01",
    "end_date": "2025-10-29",
    "start_price": 67.790001,
    "end_price": 95.760002,
    "total_return": 0.412597740713359,
    "cagr": 0.25995718413018243,
    "total_return_pct": 41.2597740713359,
    "cagr_pct": 25.995718413018242,
    "twd_return_pct": 33.024348139909975,
    "company_name": "Uber Technologies Inc"
  },
  {
    "ticker": "ISRG",
    "start_date": "2024-05-01",
    "end_date": "2025-10-29",
    "start_price": 371.700012,
    "end_price": 537.590027,
    "total_return": 0.4463008049513846,
    "cagr": 0.2799882346642659,
    "total_return_pct": 44.63008049513846,
    "cagr_pct": 27.998823466426593,
    "twd_return_pct": 36.19816615006535,
    "company_name": "Intuitive Surgical Inc"
  },
  {
    "ticker": "INTC",
    "start_date": "2024-05-01",
    "end_date": "2025-10-29",
    "start_price": 30.056479,
    "end_price": 41.34,
    "total_return": 0.375410634086232,
    "cagr": 0.23767088813316906,
    "total_return_pct": 37.5410634086232,
    "cagr_pct": 23.767088813316906,
    "twd_return_pct": 29.522437811365364,
    "company_name": "Intel Corp"
  },
  {
    "ticker": "ULVR.L",
    "start_date": "2024-05-01",
    "end_date": "2025-10-29",
    "start_price": 4137.94043,
    "end_price": 4610.0,
    "total_return": 0.11408080380416452,
    "cagr": 0.07494242623359959,
    "total_return_pct": 11.408080380416452,
    "cagr_pct": 7.494242623359959,
    "twd_return_pct": 4.913004197780535,
    "company_name": "Unilever PLC"
  },
  {
    "ticker": "HON",
    "start_date": "2024-05-01",
    "end_date": "2025-10-29",
    "start_price": 189.286621,
    "end_price": 212.889999,
    "total_return": 0.12469649550249051,
    "cagr": 0.08178361802085421,
    "total_return_pct": 12.469649550249052,
    "cagr_pct": 8.178361802085421,
    "twd_return_pct": 5.912684027022608,
    "company_name": "Honeywell International Inc"
  },
  {
    "ticker": "ETN",
    "start_date": "2024-05-01",
    "end_date": "2025-10-29",
    "start_price": 306.097534,
    "end_price": 387.75,
    "total_return": 0.2667530989399618,
    "cagr": 0.17137625885209484,
    "total_return_pct": 26.67530989399618,
    "cagr_pct": 17.137625885209484,
    "twd_return_pct": 19.290156273082104,
    "company_name": "Eaton Corp PLC"
  },
  {
    "ticker": "ELV",
    "start_date": "2024-05-01",
    "end_date": "2025-10-29",
    "start_price": 512.322388,
    "end_price": 336.359985,
    "total_return": -0.34346030267253924,
    "cagr": -0.24533252113352244,
    "total_return_pct": -34.34603026725392,
    "cagr_pct": -24.533252113352244,
    "twd_return_pct": -38.17364791985659,
    "company_name": "Elevance Health Inc"
  },
  {
    "ticker": "MU",
    "start_date": "2024-05-01",
    "end_date": "2025-10-29",
    "start_price": 109.025673,
    "end_price": 226.630005,
    "total_return": 1.0786847613817931,
    "cagr": 0.6314983025591003,
    "total_return_pct": 107.86847613817932,
    "cagr_pct": 63.14983025591003,
    "twd_return_pct": 95.74977178679154,
    "company_name": "Micron Technology Inc"
  },
  {
    "ticker": "CBA.AX",
    "start_date": "2024-05-01",
    "end_date": "2025-10-30",
    "start_price": 108.654655,
    "end_price": 170.529999,
    "total_return": 0.5694679446800262,
    "cagr": 0.35117122631532927,
    "total_return_pct": 56.946794468002615,
    "cagr_pct": 35.11712263153293,
    "twd_return_pct": 47.79681734597181,
    "company_name": "Commonwealth Bank of Australia"
  },
  {
    "ticker": "SU.PA",
    "start_date": "2024-05-02",
    "end_date": "2025-10-29",
    "start_price": 206.644348,
    "end_price": 257.399994,
    "total_return": 0.24561835931004317,
    "cagr": 0.15857846633636097,
    "total_return_pct": 24.561835931004318,
    "cagr_pct": 15.857846633636097,
    "twd_return_pct": 17.299897559404087,
    "company_name": "Schneider Electric SE"
  },
  {
    "ticker": "PGR",
    "start_date": "2024-05-01",
    "end_date": "2025-10-29",
    "start_price": 207.38176,
    "end_price": 207.970001,
    "total_return": 0.002836515507243842,
    "cagr": 0.0018966144227343662,
    "total_return_pct": 0.2836515507243842,
    "cagr_pct": 0.18966144227343662,
    "twd_return_pct": -5.562871919303614,
    "company_name": "Progressive Corp/The"
  },
  {
    "ticker": "T",
    "start_date": "2024-05-01",
    "end_date": "2025-10-29",
    "start_price": 15.752812,
    "end_price": 25.139999,
    "total_return": 0.5959054659150753,
    "cagr": 0.36710813662289943,
    "total_return_pct": 59.59054659150753,
    "cagr_pct": 36.710813662289944,
    "twd_return_pct": 50.28643907434258,
    "company_name": "AT&T Inc"
  },
  {
    "ticker": "BKNG",
    "start_date": "2024-05-01",
    "end_date": "2025-10-29",
    "start_price": 3375.697266,
    "end_price": 5075.859863,
    "total_return": 0.5036478285446815,
    "cagr": 0.3137204950611596,
    "total_return_pct": 50.364782854468146,
    "cagr_pct": 31.372049506115964,
    "twd_return_pct": 41.59853612900215,
    "company_name": "Booking Holdings Inc"
  },
  {
    "ticker": "SYK",
    "start_date": "2024-05-01",
    "end_date": "2025-10-29",
    "start_price": 323.683258,
    "end_price": 369.589996,
    "total_return": 0.14182611283904234,
    "cagr": 0.09277776217249656,
    "total_return_pct": 14.182611283904233,
    "cagr_pct": 9.277776217249656,
    "twd_return_pct": 7.525780320756015,
    "company_name": "Stryker Corp"
  },
  {
    "ticker": "LRCX",
    "start_date": "2024-05-01",
    "end_date": "2025-10-29",
    "start_price": 85.479729,
    "end_price": 160.669998,
    "total_return": 0.8796269082137547,
    "cagr": 0.52525300457292,
    "total_return_pct": 87.96269082137546,
    "cagr_pct": 52.525300457292005,
    "twd_return_pct": 77.00449109107406,
    "company_name": "Lam Research Corp"
  },
  {
    "ticker": "C",
    "start_date": "2024-05-01",
    "end_date": "2025-10-29",
    "start_price": 58.44698,
    "end_price": 99.120003,
    "total_return": 0.6958960677869859,
    "cagr": 0.42382955502538344,
    "total_return_pct": 69.58960677869858,
    "cagr_pct": 42.382955502538344,
    "twd_return_pct": 59.702555390238075,
    "company_name": "Citigroup Inc"
  },
  {
    "ticker": "BRK-A",
    "start_date": "2024-05-01",
    "end_date": "2025-10-29",
    "start_price": 602100.0,
    "end_price": 712900.0,
    "total_return": 0.18402258761003165,
    "cagr": 0.11963020713125894,
    "total_return_pct": 18.402258761003164,
    "cagr_pct": 11.963020713125893,
    "twd_return_pct": 11.49942291442063,
    "company_name": "Berkshire Hathaway Inc"
  },
  {
    "ticker": "BLK",
    "start_date": "2024-05-01",
    "end_date": "2025-10-29",
    "start_price": 727.292969,
    "end_price": 1098.0,
    "total_return": 0.5097079817602732,
    "cagr": 0.317260050600791,
    "total_return_pct": 50.97079817602732,
    "cagr_pct": 31.7260050600791,
    "twd_return_pct": 42.16922083838372,
    "company_name": "BlackRock Inc"
  },
  {
    "ticker": "8306.T",
    "start_date": "2024-05-01",
    "end_date": "2025-10-30",
    "start_price": 1487.532959,
    "end_price": 2323.0,
    "total_return": 0.5616460704077755,
    "cagr": 0.3466710254415075,
    "total_return_pct": 56.16460704077755,
    "cagr_pct": 34.66710254415075,
    "twd_return_pct": 47.060231341117365,
    "company_name": "Mitsubishi UFJ Financial Group Inc"
  },
  {
    "ticker": "TSM",
    "start_date": "2024-05-01",
    "end_date": "2025-10-29",
    "start_price": 132.176422,
    "end_price": 305.089996,
    "total_return": 1.3082028658854896,
    "cagr": 0.7499043945563693,
    "total_return_pct": 130.82028658854895,
    "cagr_pct": 74.99043945563693,
    "twd_return_pct": 117.36349475826793,
    "company_name": "Taiwan Semiconductor Manufacturing Company Limited"
  }
]